[
  {
    "name": "Bogdan Bogdanovic",
    "line": 3.5,
    "over": {
      "american": "−110",
      "trueOdds": 1.90909091
    },
    "matchup": "DEN Nuggets @ LA Clippers",
    "gameTime": "2025-04-26T22:05:00.0000000Z",
    "under": {
      "american": "−120",
      "trueOdds": 1.83333334
    }
  },
  {
    "name": "Nicolas Batum",
    "line": 5.5,
    "over": {
      "american": "−105",
      "trueOdds": 1.95238096
    },
    "matchup": "DEN Nuggets @ LA Clippers",
    "gameTime": "2025-04-26T22:05:00.0000000Z",
    "under": {
      "american": "−125",
      "trueOdds": 1.8
    }
  },
  {
    "name": "Cason Wallace",
    "line": 6.5,
    "over": {
      "american": "−110",
      "trueOdds": 1.90909091
    },
    "matchup": "OKC Thunder @ MEM Grizzlies",
    "gameTime": "2025-04-26T19:35:00.0000000Z",
    "under": {
      "american": "−120",
      "trueOdds": 1.83333334
    }
  },
  {
    "name": "Alex Caruso",
    "line": 6.5,
    "over": {
      "american": "−125",
      "trueOdds": 1.8
    },
    "matchup": "OKC Thunder @ MEM Grizzlies",
    "gameTime": "2025-04-26T19:35:00.0000000Z",
    "under": {
      "american": "−105",
      "trueOdds": 1.95238096
    }
  },
  {
    "name": "Kris Dunn",
    "line": 6.5,
    "over": {
      "american": "−125",
      "trueOdds": 1.8
    },
    "matchup": "DEN Nuggets @ LA Clippers",
    "gameTime": "2025-04-26T22:05:00.0000000Z",
    "under": {
      "american": "−105",
      "trueOdds": 1.95238096
    }
  },
  {
    "name": "Derrick Jones Jr.",
    "line": 6.5,
    "over": {
      "american": "−115",
      "trueOdds": 1.86956522
    },
    "matchup": "DEN Nuggets @ LA Clippers",
    "gameTime": "2025-04-26T22:05:00.0000000Z",
    "under": {
      "american": "−115",
      "trueOdds": 1.86956522
    }
  },
  {
    "name": "Mike Conley",
    "line": 6.5,
    "over": {
      "american": "−110",
      "trueOdds": 1.90909091
    },
    "matchup": "LA Lakers @ MIN Timberwolves",
    "gameTime": "2025-04-27T19:35:00.0000000Z",
    "under": {
      "american": "−120",
      "trueOdds": 1.83333334
    }
  },
  {
    "name": "Kentavious Caldwell-Pope",
    "line": 6.5,
    "over": {
      "american": "−130",
      "trueOdds": 1.76923077
    },
    "matchup": "BOS Celtics @ ORL Magic",
    "gameTime": "2025-04-27T23:05:00.0000000Z",
    "under": {
      "american": "+100",
      "trueOdds": 2
    }
  },
  {
    "name": "Brook Lopez",
    "line": 6.5,
    "over": {
      "american": "+100",
      "trueOdds": 2
    },
    "matchup": "IND Pacers @ MIL Bucks",
    "gameTime": "2025-04-28T01:35:00.0000000Z",
    "under": {
      "american": "−130",
      "trueOdds": 1.76923077
    }
  },
  {
    "name": "Luke Kennard",
    "line": 7.5,
    "over": {
      "american": "−135",
      "trueOdds": 1.74074075
    },
    "matchup": "OKC Thunder @ MEM Grizzlies",
    "gameTime": "2025-04-26T19:35:00.0000000Z",
    "under": {
      "american": "+105",
      "trueOdds": 2.05
    }
  },
  {
    "name": "Jabari Smith Jr.",
    "line": 7.5,
    "over": {
      "american": "−130",
      "trueOdds": 1.76923077
    },
    "matchup": "HOU Rockets @ GS Warriors",
    "gameTime": "2025-04-27T00:35:00.0000000Z",
    "under": {
      "american": "+100",
      "trueOdds": 2
    }
  },
  {
    "name": "Rudy Gobert",
    "line": 7.5,
    "over": {
      "american": "−110",
      "trueOdds": 1.90909091
    },
    "matchup": "LA Lakers @ MIN Timberwolves",
    "gameTime": "2025-04-27T19:35:00.0000000Z",
    "under": {
      "american": "−120",
      "trueOdds": 1.83333334
    }
  },
  {
    "name": "Dorian Finney-Smith",
    "line": 7.5,
    "over": {
      "american": "+105",
      "trueOdds": 2.05
    },
    "matchup": "LA Lakers @ MIN Timberwolves",
    "gameTime": "2025-04-27T19:35:00.0000000Z",
    "under": {
      "american": "−135",
      "trueOdds": 1.74074075
    }
  },
  {
    "name": "Zach Edey",
    "line": 8.5,
    "over": {
      "american": "+100",
      "trueOdds": 2
    },
    "matchup": "OKC Thunder @ MEM Grizzlies",
    "gameTime": "2025-04-26T19:35:00.0000000Z",
    "under": {
      "american": "−130",
      "trueOdds": 1.76923077
    }
  },
  {
    "name": "Isaiah Hartenstein",
    "line": 8.5,
    "over": {
      "american": "−110",
      "trueOdds": 1.90909091
    },
    "matchup": "OKC Thunder @ MEM Grizzlies",
    "gameTime": "2025-04-26T19:35:00.0000000Z",
    "under": {
      "american": "−120",
      "trueOdds": 1.83333334
    }
  },
  {
    "name": "Draymond Green",
    "line": 8.5,
    "over": {
      "american": "−130",
      "trueOdds": 1.76923077
    },
    "matchup": "HOU Rockets @ GS Warriors",
    "gameTime": "2025-04-27T00:35:00.0000000Z",
    "under": {
      "american": "+100",
      "trueOdds": 2
    }
  },
  {
    "name": "Tari Eason",
    "line": 8.5,
    "over": {
      "american": "−115",
      "trueOdds": 1.86956522
    },
    "matchup": "HOU Rockets @ GS Warriors",
    "gameTime": "2025-04-27T00:35:00.0000000Z",
    "under": {
      "american": "−115",
      "trueOdds": 1.86956522
    }
  },
  {
    "name": "Luguentz Dort",
    "line": 9.5,
    "over": {
      "american": "+105",
      "trueOdds": 2.05
    },
    "matchup": "OKC Thunder @ MEM Grizzlies",
    "gameTime": "2025-04-26T19:35:00.0000000Z",
    "under": {
      "american": "−135",
      "trueOdds": 1.74074075
    }
  },
  {
    "name": "Moses Moody",
    "line": 9.5,
    "over": {
      "american": "−115",
      "trueOdds": 1.86956522
    },
    "matchup": "HOU Rockets @ GS Warriors",
    "gameTime": "2025-04-27T00:35:00.0000000Z",
    "under": {
      "american": "−115",
      "trueOdds": 1.86956522
    }
  },
  {
    "name": "Tim Hardaway Jr.",
    "line": 9.5,
    "over": {
      "american": "−125",
      "trueOdds": 1.8
    },
    "matchup": "NY Knicks @ DET Pistons",
    "gameTime": "2025-04-27T17:05:00.0000000Z",
    "under": {
      "american": "−105",
      "trueOdds": 1.95238096
    }
  },
  {
    "name": "Ausar Thompson",
    "line": 9.5,
    "over": {
      "american": "−110",
      "trueOdds": 1.90909091
    },
    "matchup": "NY Knicks @ DET Pistons",
    "gameTime": "2025-04-27T17:05:00.0000000Z",
    "under": {
      "american": "−120",
      "trueOdds": 1.83333334
    }
  },
  {
    "name": "Wendell Carter Jr.",
    "line": 9.5,
    "over": {
      "american": "−120",
      "trueOdds": 1.83333334
    },
    "matchup": "BOS Celtics @ ORL Magic",
    "gameTime": "2025-04-27T23:05:00.0000000Z",
    "under": {
      "american": "−110",
      "trueOdds": 1.90909091
    }
  },
  {
    "name": "Kyle Kuzma",
    "line": 9.5,
    "over": {
      "american": "−130",
      "trueOdds": 1.76923077
    },
    "matchup": "IND Pacers @ MIL Bucks",
    "gameTime": "2025-04-28T01:35:00.0000000Z",
    "under": {
      "american": "+100",
      "trueOdds": 2
    }
  },
  {
    "name": "Michael Porter Jr.",
    "line": 10.5,
    "over": {
      "american": "−115",
      "trueOdds": 1.86956522
    },
    "matchup": "DEN Nuggets @ LA Clippers",
    "gameTime": "2025-04-26T22:05:00.0000000Z",
    "under": {
      "american": "−115",
      "trueOdds": 1.86956522
    }
  },
  {
    "name": "Josh Hart",
    "line": 10.5,
    "over": {
      "american": "−115",
      "trueOdds": 1.86956522
    },
    "matchup": "NY Knicks @ DET Pistons",
    "gameTime": "2025-04-27T17:05:00.0000000Z",
    "under": {
      "american": "−115",
      "trueOdds": 1.86956522
    }
  },
  {
    "name": "Andrew Nembhard",
    "line": 10.5,
    "over": {
      "american": "−120",
      "trueOdds": 1.83333334
    },
    "matchup": "IND Pacers @ MIL Bucks",
    "gameTime": "2025-04-28T01:35:00.0000000Z",
    "under": {
      "american": "−110",
      "trueOdds": 1.90909091
    }
  },
  {
    "name": "Santi Aldama",
    "line": 11.5,
    "over": {
      "american": "−130",
      "trueOdds": 1.76923077
    },
    "matchup": "OKC Thunder @ MEM Grizzlies",
    "gameTime": "2025-04-26T19:35:00.0000000Z",
    "under": {
      "american": "+100",
      "trueOdds": 2
    }
  },
  {
    "name": "Christian Braun",
    "line": 11.5,
    "over": {
      "american": "−125",
      "trueOdds": 1.8
    },
    "matchup": "DEN Nuggets @ LA Clippers",
    "gameTime": "2025-04-26T22:05:00.0000000Z",
    "under": {
      "american": "−105",
      "trueOdds": 1.95238096
    }
  },
  {
    "name": "Dennis Schroder",
    "line": 11.5,
    "over": {
      "american": "−110",
      "trueOdds": 1.90909091
    },
    "matchup": "NY Knicks @ DET Pistons",
    "gameTime": "2025-04-27T17:05:00.0000000Z",
    "under": {
      "american": "−120",
      "trueOdds": 1.83333334
    }
  },
  {
    "name": "Jalen Duren",
    "line": 11.5,
    "over": {
      "american": "+100",
      "trueOdds": 2
    },
    "matchup": "NY Knicks @ DET Pistons",
    "gameTime": "2025-04-27T17:05:00.0000000Z",
    "under": {
      "american": "−130",
      "trueOdds": 1.76923077
    }
  },
  {
    "name": "Rui Hachimura",
    "line": 11.5,
    "over": {
      "american": "−110",
      "trueOdds": 1.90909091
    },
    "matchup": "LA Lakers @ MIN Timberwolves",
    "gameTime": "2025-04-27T19:35:00.0000000Z",
    "under": {
      "american": "−120",
      "trueOdds": 1.83333334
    }
  },
  {
    "name": "Amen Thompson",
    "line": 12.5,
    "over": {
      "american": "+100",
      "trueOdds": 2
    },
    "matchup": "HOU Rockets @ GS Warriors",
    "gameTime": "2025-04-27T00:35:00.0000000Z",
    "under": {
      "american": "−130",
      "trueOdds": 1.76923077
    }
  },
  {
    "name": "Dillon Brooks",
    "line": 12.5,
    "over": {
      "american": "−115",
      "trueOdds": 1.86956522
    },
    "matchup": "HOU Rockets @ GS Warriors",
    "gameTime": "2025-04-27T00:35:00.0000000Z",
    "under": {
      "american": "−115",
      "trueOdds": 1.86956522
    }
  },
  {
    "name": "Aaron Nesmith",
    "line": 12.5,
    "over": {
      "american": "−125",
      "trueOdds": 1.8
    },
    "matchup": "IND Pacers @ MIL Bucks",
    "gameTime": "2025-04-28T01:35:00.0000000Z",
    "under": {
      "american": "−105",
      "trueOdds": 1.95238096
    }
  },
  {
    "name": "Gary Trent Jr.",
    "line": 12.5,
    "over": {
      "american": "−120",
      "trueOdds": 1.83333334
    },
    "matchup": "IND Pacers @ MIL Bucks",
    "gameTime": "2025-04-28T01:35:00.0000000Z",
    "under": {
      "american": "−110",
      "trueOdds": 1.90909091
    }
  },
  {
    "name": "Fred VanVleet",
    "line": 13.5,
    "over": {
      "american": "−120",
      "trueOdds": 1.83333334
    },
    "matchup": "HOU Rockets @ GS Warriors",
    "gameTime": "2025-04-27T00:35:00.0000000Z",
    "under": {
      "american": "−110",
      "trueOdds": 1.90909091
    }
  },
  {
    "name": "Malik Beasley",
    "line": 13.5,
    "over": {
      "american": "−125",
      "trueOdds": 1.8
    },
    "matchup": "NY Knicks @ DET Pistons",
    "gameTime": "2025-04-27T17:05:00.0000000Z",
    "under": {
      "american": "−105",
      "trueOdds": 1.95238096
    }
  },
  {
    "name": "Scotty Pippen Jr.",
    "line": 14.5,
    "over": {
      "american": "−115",
      "trueOdds": 1.86956522
    },
    "matchup": "OKC Thunder @ MEM Grizzlies",
    "gameTime": "2025-04-26T19:35:00.0000000Z",
    "under": {
      "american": "−115",
      "trueOdds": 1.86956522
    }
  },
  {
    "name": "Brandin Podziemski",
    "line": 14.5,
    "over": {
      "american": "+100",
      "trueOdds": 2
    },
    "matchup": "HOU Rockets @ GS Warriors",
    "gameTime": "2025-04-27T00:35:00.0000000Z",
    "under": {
      "american": "−130",
      "trueOdds": 1.76923077
    }
  },
  {
    "name": "Jaden McDaniels",
    "line": 14.5,
    "over": {
      "american": "−105",
      "trueOdds": 1.95238096
    },
    "matchup": "LA Lakers @ MIN Timberwolves",
    "gameTime": "2025-04-27T19:35:00.0000000Z",
    "under": {
      "american": "−125",
      "trueOdds": 1.8
    }
  },
  {
    "name": "Derrick White",
    "line": 14.5,
    "over": {
      "american": "−115",
      "trueOdds": 1.86956522
    },
    "matchup": "BOS Celtics @ ORL Magic",
    "gameTime": "2025-04-27T23:05:00.0000000Z",
    "under": {
      "american": "−115",
      "trueOdds": 1.86956522
    }
  },
  {
    "name": "Myles Turner",
    "line": 14.5,
    "over": {
      "american": "−105",
      "trueOdds": 1.95238096
    },
    "matchup": "IND Pacers @ MIL Bucks",
    "gameTime": "2025-04-28T01:35:00.0000000Z",
    "under": {
      "american": "−125",
      "trueOdds": 1.8
    }
  },
  {
    "name": "Aaron Gordon",
    "line": 15.5,
    "over": {
      "american": "−110",
      "trueOdds": 1.90909091
    },
    "matchup": "DEN Nuggets @ LA Clippers",
    "gameTime": "2025-04-26T22:05:00.0000000Z",
    "under": {
      "american": "−120",
      "trueOdds": 1.83333334
    }
  },
  {
    "name": "Tobias Harris",
    "line": 15.5,
    "over": {
      "american": "+100",
      "trueOdds": 2
    },
    "matchup": "NY Knicks @ DET Pistons",
    "gameTime": "2025-04-27T17:05:00.0000000Z",
    "under": {
      "american": "−130",
      "trueOdds": 1.76923077
    }
  },
  {
    "name": "Mikal Bridges",
    "line": 15.5,
    "over": {
      "american": "−125",
      "trueOdds": 1.8
    },
    "matchup": "NY Knicks @ DET Pistons",
    "gameTime": "2025-04-27T17:05:00.0000000Z",
    "under": {
      "american": "−105",
      "trueOdds": 1.95238096
    }
  },
  {
    "name": "Chet Holmgren",
    "line": 16.5,
    "over": {
      "american": "−120",
      "trueOdds": 1.83333334
    },
    "matchup": "OKC Thunder @ MEM Grizzlies",
    "gameTime": "2025-04-26T19:35:00.0000000Z",
    "under": {
      "american": "−110",
      "trueOdds": 1.90909091
    }
  },
  {
    "name": "Norman Powell",
    "line": 17.5,
    "over": {
      "american": "−115",
      "trueOdds": 1.86956522
    },
    "matchup": "DEN Nuggets @ LA Clippers",
    "gameTime": "2025-04-26T22:05:00.0000000Z",
    "under": {
      "american": "−115",
      "trueOdds": 1.86956522
    }
  },
  {
    "name": "Ivica Zubac",
    "line": 17.5,
    "over": {
      "american": "−125",
      "trueOdds": 1.8
    },
    "matchup": "DEN Nuggets @ LA Clippers",
    "gameTime": "2025-04-26T22:05:00.0000000Z",
    "under": {
      "american": "−105",
      "trueOdds": 1.95238096
    }
  },
  {
    "name": "OG Anunoby",
    "line": 17.5,
    "over": {
      "american": "+100",
      "trueOdds": 2
    },
    "matchup": "NY Knicks @ DET Pistons",
    "gameTime": "2025-04-27T17:05:00.0000000Z",
    "under": {
      "american": "−130",
      "trueOdds": 1.76923077
    }
  },
  {
    "name": "Kristaps Porzingis",
    "line": 17.5,
    "over": {
      "american": "−115",
      "trueOdds": 1.86956522
    },
    "matchup": "BOS Celtics @ ORL Magic",
    "gameTime": "2025-04-27T23:05:00.0000000Z",
    "under": {
      "american": "−115",
      "trueOdds": 1.86956522
    }
  },
  {
    "name": "Austin Reaves",
    "line": 18.5,
    "over": {
      "american": "−115",
      "trueOdds": 1.86956522
    },
    "matchup": "LA Lakers @ MIN Timberwolves",
    "gameTime": "2025-04-27T19:35:00.0000000Z",
    "under": {
      "american": "−115",
      "trueOdds": 1.86956522
    }
  },
  {
    "name": "Tyrese Haliburton",
    "line": 18.5,
    "over": {
      "american": "−105",
      "trueOdds": 1.95238096
    },
    "matchup": "IND Pacers @ MIL Bucks",
    "gameTime": "2025-04-28T01:35:00.0000000Z",
    "under": {
      "american": "−125",
      "trueOdds": 1.8
    }
  },
  {
    "name": "Alperen Sengun",
    "line": 19.5,
    "over": {
      "american": "−110",
      "trueOdds": 1.90909091
    },
    "matchup": "HOU Rockets @ GS Warriors",
    "gameTime": "2025-04-27T00:35:00.0000000Z",
    "under": {
      "american": "−120",
      "trueOdds": 1.83333334
    }
  },
  {
    "name": "Julius Randle",
    "line": 19.5,
    "over": {
      "american": "−110",
      "trueOdds": 1.90909091
    },
    "matchup": "LA Lakers @ MIN Timberwolves",
    "gameTime": "2025-04-27T19:35:00.0000000Z",
    "under": {
      "american": "−120",
      "trueOdds": 1.83333334
    }
  },
  {
    "name": "Jaylen Brown",
    "line": 19.5,
    "over": {
      "american": "−115",
      "trueOdds": 1.86956522
    },
    "matchup": "BOS Celtics @ ORL Magic",
    "gameTime": "2025-04-27T23:05:00.0000000Z",
    "under": {
      "american": "−115",
      "trueOdds": 1.86956522
    }
  },
  {
    "name": "Damian Lillard",
    "line": 19.5,
    "over": {
      "american": "−105",
      "trueOdds": 1.95238096
    },
    "matchup": "IND Pacers @ MIL Bucks",
    "gameTime": "2025-04-28T01:35:00.0000000Z",
    "under": {
      "american": "−125",
      "trueOdds": 1.8
    }
  },
  {
    "name": "Desmond Bane",
    "line": 20.5,
    "over": {
      "american": "+100",
      "trueOdds": 2
    },
    "matchup": "OKC Thunder @ MEM Grizzlies",
    "gameTime": "2025-04-26T19:35:00.0000000Z",
    "under": {
      "american": "−130",
      "trueOdds": 1.76923077
    }
  },
  {
    "name": "Jalen Green",
    "line": 20.5,
    "over": {
      "american": "+100",
      "trueOdds": 2
    },
    "matchup": "HOU Rockets @ GS Warriors",
    "gameTime": "2025-04-27T00:35:00.0000000Z",
    "under": {
      "american": "−130",
      "trueOdds": 1.76923077
    }
  },
  {
    "name": "Pascal Siakam",
    "line": 20.5,
    "over": {
      "american": "−125",
      "trueOdds": 1.8
    },
    "matchup": "IND Pacers @ MIL Bucks",
    "gameTime": "2025-04-28T01:35:00.0000000Z",
    "under": {
      "american": "−105",
      "trueOdds": 1.95238096
    }
  },
  {
    "name": "Jalen Williams",
    "line": 21.5,
    "over": {
      "american": "−115",
      "trueOdds": 1.86956522
    },
    "matchup": "OKC Thunder @ MEM Grizzlies",
    "gameTime": "2025-04-26T19:35:00.0000000Z",
    "under": {
      "american": "−115",
      "trueOdds": 1.86956522
    }
  },
  {
    "name": "Jamal Murray",
    "line": 21.5,
    "over": {
      "american": "−105",
      "trueOdds": 1.95238096
    },
    "matchup": "DEN Nuggets @ LA Clippers",
    "gameTime": "2025-04-26T22:05:00.0000000Z",
    "under": {
      "american": "−125",
      "trueOdds": 1.8
    }
  },
  {
    "name": "Jimmy Butler",
    "line": 21.5,
    "over": {
      "american": "−105",
      "trueOdds": 1.95238096
    },
    "matchup": "HOU Rockets @ GS Warriors",
    "gameTime": "2025-04-27T00:35:00.0000000Z",
    "under": {
      "american": "−125",
      "trueOdds": 1.8
    }
  },
  {
    "name": "Karl-Anthony Towns",
    "line": 22.5,
    "over": {
      "american": "−120",
      "trueOdds": 1.83333334
    },
    "matchup": "NY Knicks @ DET Pistons",
    "gameTime": "2025-04-27T17:05:00.0000000Z",
    "under": {
      "american": "−110",
      "trueOdds": 1.90909091
    }
  },
  {
    "name": "Jaren Jackson Jr.",
    "line": 23.5,
    "over": {
      "american": "−105",
      "trueOdds": 1.95238096
    },
    "matchup": "OKC Thunder @ MEM Grizzlies",
    "gameTime": "2025-04-26T19:35:00.0000000Z",
    "under": {
      "american": "−125",
      "trueOdds": 1.8
    }
  },
  {
    "name": "James Harden",
    "line": 23.5,
    "over": {
      "american": "−105",
      "trueOdds": 1.95238096
    },
    "matchup": "DEN Nuggets @ LA Clippers",
    "gameTime": "2025-04-26T22:05:00.0000000Z",
    "under": {
      "american": "−125",
      "trueOdds": 1.8
    }
  },
  {
    "name": "LeBron James",
    "line": 23.5,
    "over": {
      "american": "−125",
      "trueOdds": 1.8
    },
    "matchup": "LA Lakers @ MIN Timberwolves",
    "gameTime": "2025-04-27T19:35:00.0000000Z",
    "under": {
      "american": "−105",
      "trueOdds": 1.95238096
    }
  },
  {
    "name": "Franz Wagner",
    "line": 24.5,
    "over": {
      "american": "−110",
      "trueOdds": 1.90909091
    },
    "matchup": "BOS Celtics @ ORL Magic",
    "gameTime": "2025-04-27T23:05:00.0000000Z",
    "under": {
      "american": "−120",
      "trueOdds": 1.83333334
    }
  },
  {
    "name": "Kawhi Leonard",
    "line": 25.5,
    "over": {
      "american": "−110",
      "trueOdds": 1.90909091
    },
    "matchup": "DEN Nuggets @ LA Clippers",
    "gameTime": "2025-04-26T22:05:00.0000000Z",
    "under": {
      "american": "−120",
      "trueOdds": 1.83333334
    }
  },
  {
    "name": "Jayson Tatum",
    "line": 25.5,
    "over": {
      "american": "−110",
      "trueOdds": 1.90909091
    },
    "matchup": "BOS Celtics @ ORL Magic",
    "gameTime": "2025-04-27T23:05:00.0000000Z",
    "under": {
      "american": "−120",
      "trueOdds": 1.83333334
    }
  },
  {
    "name": "Stephen Curry",
    "line": 27.5,
    "over": {
      "american": "−115",
      "trueOdds": 1.86956522
    },
    "matchup": "HOU Rockets @ GS Warriors",
    "gameTime": "2025-04-27T00:35:00.0000000Z",
    "under": {
      "american": "−115",
      "trueOdds": 1.86956522
    }
  },
  {
    "name": "Cade Cunningham",
    "line": 27.5,
    "over": {
      "american": "−110",
      "trueOdds": 1.90909091
    },
    "matchup": "NY Knicks @ DET Pistons",
    "gameTime": "2025-04-27T17:05:00.0000000Z",
    "under": {
      "american": "−120",
      "trueOdds": 1.83333334
    }
  },
  {
    "name": "Nikola Jokic",
    "line": 28.5,
    "over": {
      "american": "−120",
      "trueOdds": 1.83333334
    },
    "matchup": "DEN Nuggets @ LA Clippers",
    "gameTime": "2025-04-26T22:05:00.0000000Z",
    "under": {
      "american": "−110",
      "trueOdds": 1.90909091
    }
  },
  {
    "name": "Anthony Edwards",
    "line": 28.5,
    "over": {
      "american": "−110",
      "trueOdds": 1.90909091
    },
    "matchup": "LA Lakers @ MIN Timberwolves",
    "gameTime": "2025-04-27T19:35:00.0000000Z",
    "under": {
      "american": "−120",
      "trueOdds": 1.83333334
    }
  },
  {
    "name": "Luka Doncic",
    "line": 28.5,
    "over": {
      "american": "−115",
      "trueOdds": 1.86956522
    },
    "matchup": "LA Lakers @ MIN Timberwolves",
    "gameTime": "2025-04-27T19:35:00.0000000Z",
    "under": {
      "american": "−115",
      "trueOdds": 1.86956522
    }
  },
  {
    "name": "Paolo Banchero",
    "line": 28.5,
    "over": {
      "american": "−120",
      "trueOdds": 1.83333334
    },
    "matchup": "BOS Celtics @ ORL Magic",
    "gameTime": "2025-04-27T23:05:00.0000000Z",
    "under": {
      "american": "−110",
      "trueOdds": 1.90909091
    }
  },
  {
    "name": "Jalen Brunson",
    "line": 29.5,
    "over": {
      "american": "−125",
      "trueOdds": 1.8
    },
    "matchup": "NY Knicks @ DET Pistons",
    "gameTime": "2025-04-27T17:05:00.0000000Z",
    "under": {
      "american": "−105",
      "trueOdds": 1.95238096
    }
  },
  {
    "name": "Shai Gilgeous-Alexander",
    "line": 31.5,
    "over": {
      "american": "−115",
      "trueOdds": 1.86956522
    },
    "matchup": "OKC Thunder @ MEM Grizzlies",
    "gameTime": "2025-04-26T19:35:00.0000000Z",
    "under": {
      "american": "−115",
      "trueOdds": 1.86956522
    }
  },
  {
    "name": "Giannis Antetokounmpo",
    "line": 32.5,
    "over": {
      "american": "−120",
      "trueOdds": 1.83333334
    },
    "matchup": "IND Pacers @ MIL Bucks",
    "gameTime": "2025-04-28T01:35:00.0000000Z",
    "under": {
      "american": "−110",
      "trueOdds": 1.90909091
    }
  }
]