{
    "sports": [
        {
            "id": "3",
            "seoIdentifier": "football",
            "name": "Football",
            "sortOrder": 56
        }
    ],
    "leagues": [
        {
            "id": "88808",
            "seoIdentifier": "nfl",
            "name": "NFL",
            "sportId": "3",
            "sortOrder": 4847,
            "tags": [
                "Featured"
            ],
            "isTeamSwap": true
        }
    ],
    "events": [
        {
            "id": "33447090",
            "seoIdentifier": "la-rams-%40-sea-seahawks",
            "sportId": "3",
            "leagueId": "88808",
            "name": "LA Rams @ SEA Seahawks",
            "startEventDate": "2026-01-25T23:30:00.0000000Z",
            "participants": [
                {
                    "id": "18471",
                    "name": "SEA Seahawks",
                    "venueRole": "Home",
                    "type": "Team",
                    "metadata": {
                        "retailRotNumber": "103",
                        "rosettaTeamId": "18471",
                        "rosettaTeamName": "Seahawks",
                        "shortName": "SEA",
                        "teamColor": "#002244"
                    },
                    "sortOrder": 2,
                    "seoIdentifier": "Seahawks",
                    "isNationalTeam": false,
                    "countryCode": "US"
                },
                {
                    "id": "18397",
                    "name": "LA Rams",
                    "venueRole": "Away",
                    "type": "Team",
                    "metadata": {
                        "retailRotNumber": "102",
                        "rosettaTeamId": "18397",
                        "rosettaTeamName": "Rams",
                        "shortName": "LAR",
                        "teamColor": "#003594"
                    },
                    "sortOrder": 1,
                    "seoIdentifier": "Rams",
                    "isNationalTeam": false,
                    "countryCode": "US"
                }
            ],
            "eventParticipantType": "TwoTeam",
            "status": "NOT_STARTED",
            "media": [
                {
                    "providerName": "BetGenius",
                    "providerEventId": "12891809",
                    "mediaType": "LiveStreaming",
                    "metadata": {
                        "BetGeniusDash": "Akamai",
                        "BetGeniusHls": "Akamai",
                        "BetGeniusLiveStreamId": "704ca8df"
                    },
                    "allowedDmas": [
                        "662",
                        "525",
                        "532",
                        "790",
                        "644",
                        "583",
                        "634",
                        "524",
                        "520",
                        "635",
                        "800",
                        "512",
                        "537",
                        "716",
                        "692",
                        "821",
                        "756",
                        "746",
                        "502",
                        "630",
                        "559",
                        "757",
                        "506",
                        "736",
                        "514",
                        "523",
                        "754",
                        "767",
                        "637",
                        "648",
                        "519",
                        "564",
                        "517",
                        "584",
                        "575",
                        "759",
                        "602",
                        "868",
                        "515",
                        "598",
                        "510",
                        "752",
                        "546",
                        "604",
                        "522",
                        "535",
                        "673",
                        "600",
                        "623",
                        "682",
                        "542",
                        "751",
                        "679",
                        "505",
                        "606",
                        "676",
                        "765",
                        "565",
                        "516",
                        "801",
                        "802",
                        "649",
                        "724",
                        "513",
                        "866",
                        "571",
                        "670",
                        "509",
                        "592",
                        "798",
                        "773",
                        "563",
                        "755",
                        "658",
                        "518",
                        "545",
                        "567",
                        "647",
                        "636",
                        "566",
                        "569",
                        "533",
                        "710",
                        "766",
                        "618",
                        "691",
                        "758",
                        "527",
                        "718",
                        "639",
                        "561",
                        "574",
                        "734",
                        "603",
                        "616",
                        "557",
                        "702",
                        "582",
                        "642",
                        "643",
                        "551",
                        "749",
                        "839",
                        "541",
                        "558",
                        "722",
                        "693",
                        "803",
                        "529",
                        "651",
                        "503",
                        "669",
                        "737",
                        "553",
                        "813",
                        "640",
                        "711",
                        "528",
                        "617",
                        "613",
                        "687",
                        "762",
                        "686",
                        "628",
                        "828",
                        "698",
                        "570",
                        "659",
                        "622",
                        "501",
                        "544",
                        "740",
                        "633",
                        "650",
                        "652",
                        "534",
                        "631",
                        "632",
                        "804",
                        "656",
                        "597",
                        "675",
                        "504",
                        "753",
                        "508",
                        "820",
                        "500",
                        "552",
                        "521",
                        "717",
                        "560",
                        "764",
                        "811",
                        "556",
                        "573",
                        "538",
                        "611",
                        "610",
                        "862",
                        "576",
                        "770",
                        "661",
                        "641",
                        "825",
                        "807",
                        "855",
                        "507",
                        "819",
                        "657",
                        "612",
                        "624",
                        "725",
                        "588",
                        "881",
                        "619",
                        "543",
                        "638",
                        "609",
                        "555",
                        "530",
                        "539",
                        "581",
                        "547",
                        "605",
                        "540",
                        "531",
                        "789",
                        "671",
                        "760",
                        "709",
                        "526",
                        "626",
                        "625",
                        "511",
                        "549",
                        "705",
                        "548",
                        "554",
                        "627",
                        "678",
                        "577",
                        "550",
                        "810",
                        "536",
                        "771",
                        "596",
                        "743",
                        "745",
                        "747",
                        "744"
                    ]
                },
                {
                    "providerName": "Simplebet",
                    "providerEventId": "177997cf-49fc-4614-a1b8-11c5e1b3d38f",
                    "mediaType": "MatchTracker"
                },
                {
                    "providerName": "BetRadarStats",
                    "providerEventId": "67969464",
                    "mediaType": "Stats"
                },
                {
                    "providerName": "BetRadarV3",
                    "providerEventId": "67969464",
                    "mediaType": "MatchTracker",
                    "metadata": {
                        "betRadarCoverage": "3"
                    }
                },
                {
                    "providerName": "BetRadarV3",
                    "providerEventId": "67969464",
                    "mediaType": "Scoreboard",
                    "metadata": {
                        "betRadarCoverage": "3"
                    }
                }
            ],
            "tags": [
                "FeaturedSubcategory",
                "LiveStreaming",
                "MatchTracker",
                "PrePack",
                "SGP",
                "Scoreboard",
                "SgpDynamicOdds",
                "Stats",
                "YourBetEligible"
            ],
            "metadata": {
                "masterLeagueId": "40",
                "numberOfParts": "4",
                "secondsInOnePart": "900"
            },
            "sortOrder": 213981090,
            "subscriptionKey": "events-49311580-45110647"
        }
    ],
    "markets": [
        {
            "id": "304042868",
            "eventId": "33447090",
            "sportId": "3",
            "leagueId": "88808",
            "name": "Ernest Jones Tackles O/U",
            "subcategoryId": "18539",
            "componentMapping": {
                "primary": 8,
                "fallback": 0
            },
            "marketType": {
                "id": "13687",
                "betOfferTypeId": 0,
                "name": "Tackles O/U"
            },
            "subscriptionKey": "events-49311580-45110647",
            "sortOrder": 1,
            "tags": [
                "YourBetEligible",
                "Cashout",
                "IgnoreSortOrderOnPush",
                "MicroMarketDelayRemoval",
                "PlayerProps"
            ],
            "correlatedId": "33447090|13687|2:122701",
            "blurbId": "d917765d-8a8d-4981-a689-c8bfb86cc0e5",
            "dynamicMetadata": {}
        },
        {
            "id": "304043362",
            "eventId": "33447090",
            "sportId": "3",
            "leagueId": "88808",
            "name": "Kamren Curl Tackles O/U",
            "subcategoryId": "18539",
            "componentMapping": {
                "primary": 8,
                "fallback": 0
            },
            "marketType": {
                "id": "13687",
                "betOfferTypeId": 0,
                "name": "Tackles O/U"
            },
            "subscriptionKey": "events-49311580-45110647",
            "sortOrder": 2,
            "tags": [
                "YourBetEligible",
                "Cashout",
                "IgnoreSortOrderOnPush",
                "MicroMarketDelayRemoval",
                "PlayerProps"
            ],
            "correlatedId": "33447090|13687|2:112015",
            "blurbId": "d917765d-8a8d-4981-a689-c8bfb86cc0e5",
            "dynamicMetadata": {}
        },
        {
            "id": "304043060",
            "eventId": "33447090",
            "sportId": "3",
            "leagueId": "88808",
            "name": "Nate Landman Tackles O/U",
            "subcategoryId": "18539",
            "componentMapping": {
                "primary": 8,
                "fallback": 0
            },
            "marketType": {
                "id": "13687",
                "betOfferTypeId": 0,
                "name": "Tackles O/U"
            },
            "subscriptionKey": "events-49311580-45110647",
            "sortOrder": 3,
            "tags": [
                "YourBetEligible",
                "Cashout",
                "IgnoreSortOrderOnPush",
                "MicroMarketDelayRemoval",
                "PlayerProps"
            ],
            "correlatedId": "33447090|13687|2:136600",
            "blurbId": "d917765d-8a8d-4981-a689-c8bfb86cc0e5",
            "dynamicMetadata": {}
        },
        {
            "id": "304043422",
            "eventId": "33447090",
            "sportId": "3",
            "leagueId": "88808",
            "name": "Nick Emmanwori Tackles O/U",
            "subcategoryId": "18539",
            "componentMapping": {
                "primary": 8,
                "fallback": 0
            },
            "marketType": {
                "id": "13687",
                "betOfferTypeId": 0,
                "name": "Tackles O/U"
            },
            "subscriptionKey": "events-49311580-45110647",
            "sortOrder": 4,
            "tags": [
                "YourBetEligible",
                "Cashout",
                "IgnoreSortOrderOnPush",
                "MicroMarketDelayRemoval",
                "PlayerProps"
            ],
            "correlatedId": "33447090|13687|2:174100",
            "blurbId": "d917765d-8a8d-4981-a689-c8bfb86cc0e5",
            "dynamicMetadata": {}
        },
        {
            "id": "304042467",
            "eventId": "33447090",
            "sportId": "3",
            "leagueId": "88808",
            "name": "Devon Witherspoon Tackles O/U",
            "subcategoryId": "18539",
            "componentMapping": {
                "primary": 8,
                "fallback": 0
            },
            "marketType": {
                "id": "13687",
                "betOfferTypeId": 0,
                "name": "Tackles O/U"
            },
            "subscriptionKey": "events-49311580-45110647",
            "sortOrder": 5,
            "tags": [
                "YourBetEligible",
                "Cashout",
                "IgnoreSortOrderOnPush",
                "MicroMarketDelayRemoval",
                "PlayerProps"
            ],
            "correlatedId": "33447090|13687|2:144345",
            "blurbId": "d917765d-8a8d-4981-a689-c8bfb86cc0e5",
            "dynamicMetadata": {}
        },
        {
            "id": "304042785",
            "eventId": "33447090",
            "sportId": "3",
            "leagueId": "88808",
            "name": "Quentin Lake Tackles O/U",
            "subcategoryId": "18539",
            "componentMapping": {
                "primary": 8,
                "fallback": 0
            },
            "marketType": {
                "id": "13687",
                "betOfferTypeId": 0,
                "name": "Tackles O/U"
            },
            "subscriptionKey": "events-49311580-45110647",
            "sortOrder": 6,
            "tags": [
                "YourBetEligible",
                "Cashout",
                "IgnoreSortOrderOnPush",
                "MicroMarketDelayRemoval",
                "PlayerProps"
            ],
            "correlatedId": "33447090|13687|2:145919",
            "blurbId": "d917765d-8a8d-4981-a689-c8bfb86cc0e5",
            "dynamicMetadata": {}
        },
        {
            "id": "304043075",
            "eventId": "33447090",
            "sportId": "3",
            "leagueId": "88808",
            "name": "Julian Love Tackles O/U",
            "subcategoryId": "18539",
            "componentMapping": {
                "primary": 8,
                "fallback": 0
            },
            "marketType": {
                "id": "13687",
                "betOfferTypeId": 0,
                "name": "Tackles O/U"
            },
            "subscriptionKey": "events-49311580-45110647",
            "sortOrder": 7,
            "tags": [
                "YourBetEligible",
                "Cashout",
                "IgnoreSortOrderOnPush",
                "MicroMarketDelayRemoval",
                "PlayerProps"
            ],
            "correlatedId": "33447090|13687|2:59853",
            "blurbId": "d917765d-8a8d-4981-a689-c8bfb86cc0e5",
            "dynamicMetadata": {}
        },
        {
            "id": "304042383",
            "eventId": "33447090",
            "sportId": "3",
            "leagueId": "88808",
            "name": "Omar Speights Tackles O/U",
            "subcategoryId": "18539",
            "componentMapping": {
                "primary": 8,
                "fallback": 0
            },
            "marketType": {
                "id": "13687",
                "betOfferTypeId": 0,
                "name": "Tackles O/U"
            },
            "subscriptionKey": "events-49311580-45110647",
            "sortOrder": 8,
            "tags": [
                "YourBetEligible",
                "Cashout",
                "IgnoreSortOrderOnPush",
                "MicroMarketDelayRemoval",
                "PlayerProps"
            ],
            "correlatedId": "33447090|13687|2:139618",
            "blurbId": "d917765d-8a8d-4981-a689-c8bfb86cc0e5",
            "dynamicMetadata": {}
        },
        {
            "id": "304042647",
            "eventId": "33447090",
            "sportId": "3",
            "leagueId": "88808",
            "name": "Drake Thomas Tackles O/U",
            "subcategoryId": "18539",
            "componentMapping": {
                "primary": 8,
                "fallback": 0
            },
            "marketType": {
                "id": "13687",
                "betOfferTypeId": 0,
                "name": "Tackles O/U"
            },
            "subscriptionKey": "events-49311580-45110647",
            "sortOrder": 9,
            "tags": [
                "YourBetEligible",
                "Cashout",
                "IgnoreSortOrderOnPush",
                "MicroMarketDelayRemoval",
                "PlayerProps"
            ],
            "correlatedId": "33447090|13687|2:140105",
            "blurbId": "d917765d-8a8d-4981-a689-c8bfb86cc0e5",
            "dynamicMetadata": {}
        },
        {
            "id": "304043477",
            "eventId": "33447090",
            "sportId": "3",
            "leagueId": "88808",
            "name": "Coby Bryant Tackles O/U",
            "subcategoryId": "18539",
            "componentMapping": {
                "primary": 8,
                "fallback": 0
            },
            "marketType": {
                "id": "13687",
                "betOfferTypeId": 0,
                "name": "Tackles O/U"
            },
            "subscriptionKey": "events-49311580-45110647",
            "sortOrder": 10,
            "tags": [
                "YourBetEligible",
                "Cashout",
                "IgnoreSortOrderOnPush",
                "MicroMarketDelayRemoval",
                "PlayerProps"
            ],
            "correlatedId": "33447090|13687|2:138244",
            "blurbId": "d917765d-8a8d-4981-a689-c8bfb86cc0e5",
            "dynamicMetadata": {}
        },
        {
            "id": "304043164",
            "eventId": "33447090",
            "sportId": "3",
            "leagueId": "88808",
            "name": "Jared Verse Tackles O/U",
            "subcategoryId": "18539",
            "componentMapping": {
                "primary": 8,
                "fallback": 0
            },
            "marketType": {
                "id": "13687",
                "betOfferTypeId": 0,
                "name": "Tackles O/U"
            },
            "subscriptionKey": "events-49311580-45110647",
            "sortOrder": 11,
            "tags": [
                "YourBetEligible",
                "Cashout",
                "IgnoreSortOrderOnPush",
                "MicroMarketDelayRemoval",
                "PlayerProps"
            ],
            "correlatedId": "33447090|13687|2:168730",
            "blurbId": "d917765d-8a8d-4981-a689-c8bfb86cc0e5",
            "dynamicMetadata": {}
        },
        {
            "id": "304043275",
            "eventId": "33447090",
            "sportId": "3",
            "leagueId": "88808",
            "name": "DeMarcus Lawrence Tackles O/U",
            "subcategoryId": "18539",
            "componentMapping": {
                "primary": 8,
                "fallback": 0
            },
            "marketType": {
                "id": "13687",
                "betOfferTypeId": 0,
                "name": "Tackles O/U"
            },
            "subscriptionKey": "events-49311580-45110647",
            "sortOrder": 12,
            "tags": [
                "YourBetEligible",
                "Cashout",
                "IgnoreSortOrderOnPush",
                "MicroMarketDelayRemoval",
                "PlayerProps"
            ],
            "correlatedId": "33447090|13687|2:59534",
            "blurbId": "d917765d-8a8d-4981-a689-c8bfb86cc0e5",
            "dynamicMetadata": {}
        },
        {
            "id": "304042991",
            "eventId": "33447090",
            "sportId": "3",
            "leagueId": "88808",
            "name": "Byron Young (LAR) Tackles O/U",
            "subcategoryId": "18539",
            "componentMapping": {
                "primary": 8,
                "fallback": 0
            },
            "marketType": {
                "id": "13687",
                "betOfferTypeId": 0,
                "name": "Tackles O/U"
            },
            "subscriptionKey": "events-49311580-45110647",
            "sortOrder": 13,
            "tags": [
                "YourBetEligible",
                "Cashout",
                "IgnoreSortOrderOnPush",
                "MicroMarketDelayRemoval",
                "PlayerProps"
            ],
            "correlatedId": "33447090|13687|2:164744",
            "blurbId": "d917765d-8a8d-4981-a689-c8bfb86cc0e5",
            "dynamicMetadata": {}
        },
        {
            "id": "304042707",
            "eventId": "33447090",
            "sportId": "3",
            "leagueId": "88808",
            "name": "Leonard Williams Tackles O/U",
            "subcategoryId": "18539",
            "componentMapping": {
                "primary": 8,
                "fallback": 0
            },
            "marketType": {
                "id": "13687",
                "betOfferTypeId": 0,
                "name": "Tackles O/U"
            },
            "subscriptionKey": "events-49311580-45110647",
            "sortOrder": 14,
            "tags": [
                "YourBetEligible",
                "Cashout",
                "IgnoreSortOrderOnPush",
                "MicroMarketDelayRemoval",
                "PlayerProps"
            ],
            "correlatedId": "33447090|13687|2:59891",
            "blurbId": "d917765d-8a8d-4981-a689-c8bfb86cc0e5",
            "dynamicMetadata": {}
        },
        {
            "id": "304043306",
            "eventId": "33447090",
            "sportId": "3",
            "leagueId": "88808",
            "name": "Kobie Turner Tackles O/U",
            "subcategoryId": "18539",
            "componentMapping": {
                "primary": 8,
                "fallback": 0
            },
            "marketType": {
                "id": "13687",
                "betOfferTypeId": 0,
                "name": "Tackles O/U"
            },
            "subscriptionKey": "events-49311580-45110647",
            "sortOrder": 15,
            "tags": [
                "YourBetEligible",
                "Cashout",
                "IgnoreSortOrderOnPush",
                "MicroMarketDelayRemoval",
                "PlayerProps"
            ],
            "correlatedId": "33447090|13687|2:164741",
            "blurbId": "d917765d-8a8d-4981-a689-c8bfb86cc0e5",
            "dynamicMetadata": {}
        },
        {
            "id": "304042445",
            "eventId": "33447090",
            "sportId": "3",
            "leagueId": "88808",
            "name": "Byron Murphy II Tackles O/U",
            "subcategoryId": "18539",
            "componentMapping": {
                "primary": 8,
                "fallback": 0
            },
            "marketType": {
                "id": "13687",
                "betOfferTypeId": 0,
                "name": "Tackles O/U"
            },
            "subscriptionKey": "events-49311580-45110647",
            "sortOrder": 16,
            "tags": [
                "YourBetEligible",
                "Cashout",
                "IgnoreSortOrderOnPush",
                "MicroMarketDelayRemoval",
                "PlayerProps"
            ],
            "correlatedId": "33447090|13687|2:139118",
            "blurbId": "d917765d-8a8d-4981-a689-c8bfb86cc0e5",
            "dynamicMetadata": {}
        },
        {
            "id": "304042765",
            "eventId": "33447090",
            "sportId": "3",
            "leagueId": "88808",
            "name": "Poona Ford Tackles O/U",
            "subcategoryId": "18539",
            "componentMapping": {
                "primary": 8,
                "fallback": 0
            },
            "marketType": {
                "id": "13687",
                "betOfferTypeId": 0,
                "name": "Tackles O/U"
            },
            "subscriptionKey": "events-49311580-45110647",
            "sortOrder": 17,
            "tags": [
                "YourBetEligible",
                "Cashout",
                "IgnoreSortOrderOnPush",
                "MicroMarketDelayRemoval",
                "PlayerProps"
            ],
            "correlatedId": "33447090|13687|2:60053",
            "blurbId": "d917765d-8a8d-4981-a689-c8bfb86cc0e5",
            "dynamicMetadata": {}
        }
    ],
    "selections": [
        {
            "id": "0QA304042383#472035785_13L88808Q1383535549Q20",
            "marketId": "304042383",
            "label": "Over",
            "displayOdds": {
                "american": "−166",
                "decimal": "1.60",
                "fractional": "50/83"
            },
            "trueOdds": 1.60240964,
            "points": 2.5,
            "outcomeType": "Over",
            "participants": [
                {
                    "id": "788565",
                    "name": "Omar Speights",
                    "type": "Player",
                    "seoIdentifier": "Omar Speights",
                    "statistic": {
                        "prefix": "TCKPG",
                        "value": 2.8
                    },
                    "venueRole": "AwayPlayer",
                    "isNationalTeam": false
                }
            ],
            "sortOrder": 2500,
            "tags": [
                "MainPointLine"
            ],
            "metadata": {}
        },
        {
            "id": "0QA304042383#472035786_13L88808Q1801814857Q20",
            "marketId": "304042383",
            "label": "Under",
            "displayOdds": {
                "american": "+128",
                "decimal": "2.28",
                "fractional": "32/25"
            },
            "trueOdds": 2.28,
            "points": 2.5,
            "outcomeType": "Under",
            "participants": [
                {
                    "id": "788565",
                    "name": "Omar Speights",
                    "type": "Player",
                    "seoIdentifier": "Omar Speights",
                    "statistic": {
                        "prefix": "TCKPG",
                        "value": 2.8
                    },
                    "venueRole": "AwayPlayer",
                    "isNationalTeam": false
                }
            ],
            "sortOrder": 2502,
            "tags": [
                "MainPointLine"
            ],
            "metadata": {}
        },
        {
            "id": "0QA304042445#467601459_13L88808Q1931321776Q20",
            "marketId": "304042445",
            "label": "Over",
            "displayOdds": {
                "american": "+117",
                "decimal": "2.17",
                "fractional": "117/100"
            },
            "trueOdds": 2.17,
            "points": 1.5,
            "outcomeType": "Over",
            "participants": [
                {
                    "id": "787664",
                    "name": "Byron Murphy II",
                    "type": "Player",
                    "seoIdentifier": "Byron Murphy II",
                    "statistic": {
                        "prefix": "TCKPG",
                        "value": 1.3
                    },
                    "venueRole": "HomePlayer",
                    "isNationalTeam": false
                }
            ],
            "sortOrder": 1500,
            "tags": [
                "MainPointLine"
            ],
            "metadata": {}
        },
        {
            "id": "0QA304042445#467601477_13L88808Q1-825330146Q20",
            "marketId": "304042445",
            "label": "Under",
            "displayOdds": {
                "american": "−151",
                "decimal": "1.66",
                "fractional": "100/151"
            },
            "trueOdds": 1.66225166,
            "points": 1.5,
            "outcomeType": "Under",
            "participants": [
                {
                    "id": "787664",
                    "name": "Byron Murphy II",
                    "type": "Player",
                    "seoIdentifier": "Byron Murphy II",
                    "statistic": {
                        "prefix": "TCKPG",
                        "value": 1.3
                    },
                    "venueRole": "HomePlayer",
                    "isNationalTeam": false
                }
            ],
            "sortOrder": 1502,
            "tags": [
                "MainPointLine"
            ],
            "metadata": {}
        },
        {
            "id": "0QA304042467#467601494_13L88808Q1-862046153Q20",
            "marketId": "304042467",
            "label": "Over",
            "displayOdds": {
                "american": "−141",
                "decimal": "1.70",
                "fractional": "100/141"
            },
            "trueOdds": 1.70921986,
            "points": 3.5,
            "outcomeType": "Over",
            "participants": [
                {
                    "id": "700856",
                    "name": "Devon Witherspoon",
                    "type": "Player",
                    "seoIdentifier": "Devon Witherspoon",
                    "statistic": {
                        "prefix": "TCKPG",
                        "value": 3.9
                    },
                    "venueRole": "HomePlayer",
                    "isNationalTeam": false
                }
            ],
            "sortOrder": 3500,
            "tags": [
                "MainPointLine",
                "3rdFavorite"
            ],
            "metadata": {}
        },
        {
            "id": "0QA304042467#467601515_13L88808Q1-1234571808Q20",
            "marketId": "304042467",
            "label": "Under",
            "displayOdds": {
                "american": "+108",
                "decimal": "2.08",
                "fractional": "27/25"
            },
            "trueOdds": 2.08,
            "points": 3.5,
            "outcomeType": "Under",
            "participants": [
                {
                    "id": "700856",
                    "name": "Devon Witherspoon",
                    "type": "Player",
                    "seoIdentifier": "Devon Witherspoon",
                    "statistic": {
                        "prefix": "TCKPG",
                        "value": 3.9
                    },
                    "venueRole": "HomePlayer",
                    "isNationalTeam": false
                }
            ],
            "sortOrder": 3502,
            "tags": [
                "MainPointLine",
                "3rdFavorite"
            ],
            "metadata": {}
        },
        {
            "id": "0QA304042647#467601768_13L88808Q1383535549Q20",
            "marketId": "304042647",
            "label": "Over",
            "displayOdds": {
                "american": "−121",
                "decimal": "1.82",
                "fractional": "100/121"
            },
            "trueOdds": 1.82644629,
            "points": 2.5,
            "outcomeType": "Over",
            "participants": [
                {
                    "id": "708440",
                    "name": "Drake Thomas",
                    "type": "Player",
                    "seoIdentifier": "Drake Thomas",
                    "statistic": {
                        "prefix": "TCKPG",
                        "value": 2.8
                    },
                    "venueRole": "HomePlayer",
                    "isNationalTeam": false
                }
            ],
            "sortOrder": 2500,
            "tags": [
                "MainPointLine"
            ],
            "metadata": {}
        },
        {
            "id": "0QA304042647#467601798_13L88808Q1801814857Q20",
            "marketId": "304042647",
            "label": "Under",
            "displayOdds": {
                "american": "−107",
                "decimal": "1.93",
                "fractional": "100/107"
            },
            "trueOdds": 1.93457944,
            "points": 2.5,
            "outcomeType": "Under",
            "participants": [
                {
                    "id": "708440",
                    "name": "Drake Thomas",
                    "type": "Player",
                    "seoIdentifier": "Drake Thomas",
                    "statistic": {
                        "prefix": "TCKPG",
                        "value": 2.8
                    },
                    "venueRole": "HomePlayer",
                    "isNationalTeam": false
                }
            ],
            "sortOrder": 2502,
            "tags": [
                "MainPointLine"
            ],
            "metadata": {}
        },
        {
            "id": "0QA304042707#468775093_13L88808Q1931321776Q20",
            "marketId": "304042707",
            "label": "Over",
            "displayOdds": {
                "american": "−105",
                "decimal": "1.95",
                "fractional": "20/21"
            },
            "trueOdds": 1.95238096,
            "points": 1.5,
            "outcomeType": "Over",
            "participants": [
                {
                    "id": "19731",
                    "name": "Leonard Williams",
                    "type": "Player",
                    "seoIdentifier": "Leonard Williams",
                    "statistic": {
                        "prefix": "TCKPG",
                        "value": 1.9
                    },
                    "venueRole": "HomePlayer",
                    "isNationalTeam": false
                }
            ],
            "sortOrder": 1500,
            "tags": [
                "MainPointLine"
            ],
            "metadata": {}
        },
        {
            "id": "0QA304042707#468775094_13L88808Q1-825330146Q20",
            "marketId": "304042707",
            "label": "Under",
            "displayOdds": {
                "american": "−123",
                "decimal": "1.81",
                "fractional": "100/123"
            },
            "trueOdds": 1.81300814,
            "points": 1.5,
            "outcomeType": "Under",
            "participants": [
                {
                    "id": "19731",
                    "name": "Leonard Williams",
                    "type": "Player",
                    "seoIdentifier": "Leonard Williams",
                    "statistic": {
                        "prefix": "TCKPG",
                        "value": 1.9
                    },
                    "venueRole": "HomePlayer",
                    "isNationalTeam": false
                }
            ],
            "sortOrder": 1502,
            "tags": [
                "MainPointLine"
            ],
            "metadata": {}
        },
        {
            "id": "0QA304042765#472037822_13L88808Q1931321776Q20",
            "marketId": "304042765",
            "label": "Over",
            "displayOdds": {
                "american": "+170",
                "decimal": "2.70",
                "fractional": "17/10"
            },
            "trueOdds": 2.7,
            "points": 1.5,
            "outcomeType": "Over",
            "participants": [
                {
                    "id": "19847",
                    "name": "Poona Ford",
                    "type": "Player",
                    "seoIdentifier": "Poona Ford",
                    "statistic": {
                        "prefix": "TCKPG",
                        "value": 1.3
                    },
                    "venueRole": "AwayPlayer",
                    "isNationalTeam": false
                }
            ],
            "sortOrder": 1500,
            "tags": [
                "MainPointLine"
            ],
            "metadata": {}
        },
        {
            "id": "0QA304042765#472037823_13L88808Q1-825330146Q20",
            "marketId": "304042765",
            "label": "Under",
            "displayOdds": {
                "american": "−223",
                "decimal": "1.44",
                "fractional": "100/223"
            },
            "trueOdds": 1.4484305,
            "points": 1.5,
            "outcomeType": "Under",
            "participants": [
                {
                    "id": "19847",
                    "name": "Poona Ford",
                    "type": "Player",
                    "seoIdentifier": "Poona Ford",
                    "statistic": {
                        "prefix": "TCKPG",
                        "value": 1.3
                    },
                    "venueRole": "AwayPlayer",
                    "isNationalTeam": false
                }
            ],
            "sortOrder": 1502,
            "tags": [
                "MainPointLine"
            ],
            "metadata": {}
        },
        {
            "id": "0QA304042785#472036937_13L88808Q1-862046153Q20",
            "marketId": "304042785",
            "label": "Over",
            "displayOdds": {
                "american": "−121",
                "decimal": "1.82",
                "fractional": "100/121"
            },
            "trueOdds": 1.82644629,
            "points": 3.5,
            "outcomeType": "Over",
            "participants": [
                {
                    "id": "641105",
                    "name": "Quentin Lake",
                    "type": "Player",
                    "seoIdentifier": "Quentin Lake",
                    "statistic": {
                        "prefix": "TCKPG",
                        "value": 3.6
                    },
                    "venueRole": "AwayPlayer",
                    "isNationalTeam": false
                }
            ],
            "sortOrder": 3500,
            "tags": [
                "MainPointLine",
                "3rdFavorite"
            ],
            "metadata": {}
        },
        {
            "id": "0QA304042785#472036938_13L88808Q1-1234571808Q20",
            "marketId": "304042785",
            "label": "Under",
            "displayOdds": {
                "american": "−107",
                "decimal": "1.93",
                "fractional": "100/107"
            },
            "trueOdds": 1.93457944,
            "points": 3.5,
            "outcomeType": "Under",
            "participants": [
                {
                    "id": "641105",
                    "name": "Quentin Lake",
                    "type": "Player",
                    "seoIdentifier": "Quentin Lake",
                    "statistic": {
                        "prefix": "TCKPG",
                        "value": 3.6
                    },
                    "venueRole": "AwayPlayer",
                    "isNationalTeam": false
                }
            ],
            "sortOrder": 3502,
            "tags": [
                "MainPointLine",
                "3rdFavorite"
            ],
            "metadata": {}
        },
        {
            "id": "0QA304042868#468756306_13L88808Q1-1302256359Q20",
            "marketId": "304042868",
            "label": "Over",
            "displayOdds": {
                "american": "+100",
                "decimal": "2.00",
                "fractional": "1/1"
            },
            "trueOdds": 2,
            "points": 4.5,
            "outcomeType": "Over",
            "participants": [
                {
                    "id": "560776",
                    "name": "Ernest Jones",
                    "type": "Player",
                    "seoIdentifier": "Ernest Jones IV",
                    "statistic": {
                        "prefix": "TCKPG",
                        "value": 4
                    },
                    "venueRole": "HomePlayer",
                    "isNationalTeam": false
                }
            ],
            "sortOrder": 4500,
            "tags": [
                "MainPointLine",
                "1stFavorite"
            ],
            "metadata": {}
        },
        {
            "id": "0QA304042868#468756307_13L88808Q1-1620814556Q20",
            "marketId": "304042868",
            "label": "Under",
            "displayOdds": {
                "american": "−129",
                "decimal": "1.77",
                "fractional": "100/129"
            },
            "trueOdds": 1.7751938,
            "points": 4.5,
            "outcomeType": "Under",
            "participants": [
                {
                    "id": "560776",
                    "name": "Ernest Jones",
                    "type": "Player",
                    "seoIdentifier": "Ernest Jones IV",
                    "statistic": {
                        "prefix": "TCKPG",
                        "value": 4
                    },
                    "venueRole": "HomePlayer",
                    "isNationalTeam": false
                }
            ],
            "sortOrder": 4502,
            "tags": [
                "MainPointLine",
                "1stFavorite"
            ],
            "metadata": {}
        },
        {
            "id": "0QA304042991#472024280_13L88808Q1931321776Q20",
            "marketId": "304042991",
            "label": "Over",
            "displayOdds": {
                "american": "−111",
                "decimal": "1.90",
                "fractional": "100/111"
            },
            "trueOdds": 1.90090091,
            "points": 1.5,
            "outcomeType": "Over",
            "participants": [
                {
                    "id": "706552",
                    "name": "Byron Young (LAR)",
                    "type": "Player",
                    "seoIdentifier": "Byron Young",
                    "statistic": {
                        "prefix": "TCKPG",
                        "value": 2.5
                    },
                    "venueRole": "AwayPlayer",
                    "isNationalTeam": false
                }
            ],
            "sortOrder": 1500,
            "tags": [
                "MainPointLine"
            ],
            "metadata": {}
        },
        {
            "id": "0QA304042991#472024281_13L88808Q1-825330146Q20",
            "marketId": "304042991",
            "label": "Under",
            "displayOdds": {
                "american": "−117",
                "decimal": "1.85",
                "fractional": "100/117"
            },
            "trueOdds": 1.85470086,
            "points": 1.5,
            "outcomeType": "Under",
            "participants": [
                {
                    "id": "706552",
                    "name": "Byron Young (LAR)",
                    "type": "Player",
                    "seoIdentifier": "Byron Young",
                    "statistic": {
                        "prefix": "TCKPG",
                        "value": 2.5
                    },
                    "venueRole": "AwayPlayer",
                    "isNationalTeam": false
                }
            ],
            "sortOrder": 1502,
            "tags": [
                "MainPointLine"
            ],
            "metadata": {}
        },
        {
            "id": "0QA304043060#468745124_13L88808Q1-1302256359Q20",
            "marketId": "304043060",
            "label": "Over",
            "displayOdds": {
                "american": "+121",
                "decimal": "2.21",
                "fractional": "121/100"
            },
            "trueOdds": 2.21,
            "points": 4.5,
            "outcomeType": "Over",
            "participants": [
                {
                    "id": "641335",
                    "name": "Nate Landman",
                    "type": "Player",
                    "seoIdentifier": "Nate Landman",
                    "statistic": {
                        "prefix": "TCKPG",
                        "value": 3.9
                    },
                    "venueRole": "AwayPlayer",
                    "isNationalTeam": false
                }
            ],
            "sortOrder": 4500,
            "tags": [
                "MainPointLine",
                "2ndFavorite"
            ],
            "metadata": {}
        },
        {
            "id": "0QA304043060#468745125_13L88808Q1-1620814556Q20",
            "marketId": "304043060",
            "label": "Under",
            "displayOdds": {
                "american": "−157",
                "decimal": "1.63",
                "fractional": "100/157"
            },
            "trueOdds": 1.63694268,
            "points": 4.5,
            "outcomeType": "Under",
            "participants": [
                {
                    "id": "641335",
                    "name": "Nate Landman",
                    "type": "Player",
                    "seoIdentifier": "Nate Landman",
                    "statistic": {
                        "prefix": "TCKPG",
                        "value": 3.9
                    },
                    "venueRole": "AwayPlayer",
                    "isNationalTeam": false
                }
            ],
            "sortOrder": 4502,
            "tags": [
                "MainPointLine",
                "2ndFavorite"
            ],
            "metadata": {}
        },
        {
            "id": "0QA304043075#476038783_13L88808Q1-862046153Q20",
            "marketId": "304043075",
            "label": "Over",
            "displayOdds": {
                "american": "+123",
                "decimal": "2.23",
                "fractional": "123/100"
            },
            "trueOdds": 2.23,
            "points": 3.5,
            "outcomeType": "Over",
            "participants": [
                {
                    "id": "19194",
                    "name": "Julian Love",
                    "type": "Player",
                    "seoIdentifier": "Julian Love",
                    "statistic": {
                        "prefix": "TCKPG",
                        "value": 2.7
                    },
                    "venueRole": "HomePlayer",
                    "isNationalTeam": false
                }
            ],
            "sortOrder": 3500,
            "tags": [
                "MainPointLine"
            ],
            "metadata": {}
        },
        {
            "id": "0QA304043075#476038784_13L88808Q1-1234571808Q20",
            "marketId": "304043075",
            "label": "Under",
            "displayOdds": {
                "american": "−160",
                "decimal": "1.62",
                "fractional": "5/8"
            },
            "trueOdds": 1.625,
            "points": 3.5,
            "outcomeType": "Under",
            "participants": [
                {
                    "id": "19194",
                    "name": "Julian Love",
                    "type": "Player",
                    "seoIdentifier": "Julian Love",
                    "statistic": {
                        "prefix": "TCKPG",
                        "value": 2.7
                    },
                    "venueRole": "HomePlayer",
                    "isNationalTeam": false
                }
            ],
            "sortOrder": 3502,
            "tags": [
                "MainPointLine"
            ],
            "metadata": {}
        },
        {
            "id": "0QA304043164#472032630_13L88808Q1931321776Q20",
            "marketId": "304043164",
            "label": "Over",
            "displayOdds": {
                "american": "−157",
                "decimal": "1.63",
                "fractional": "100/157"
            },
            "trueOdds": 1.63694268,
            "points": 1.5,
            "outcomeType": "Over",
            "participants": [
                {
                    "id": "787666",
                    "name": "Jared Verse",
                    "type": "Player",
                    "seoIdentifier": "Jared Verse",
                    "statistic": {
                        "prefix": "TCKPG",
                        "value": 2
                    },
                    "venueRole": "AwayPlayer",
                    "isNationalTeam": false
                }
            ],
            "sortOrder": 1500,
            "tags": [
                "MainPointLine"
            ],
            "metadata": {}
        },
        {
            "id": "0QA304043164#472032631_13L88808Q1-825330146Q20",
            "marketId": "304043164",
            "label": "Under",
            "displayOdds": {
                "american": "+121",
                "decimal": "2.21",
                "fractional": "121/100"
            },
            "trueOdds": 2.21,
            "points": 1.5,
            "outcomeType": "Under",
            "participants": [
                {
                    "id": "787666",
                    "name": "Jared Verse",
                    "type": "Player",
                    "seoIdentifier": "Jared Verse",
                    "statistic": {
                        "prefix": "TCKPG",
                        "value": 2
                    },
                    "venueRole": "AwayPlayer",
                    "isNationalTeam": false
                }
            ],
            "sortOrder": 1502,
            "tags": [
                "MainPointLine"
            ],
            "metadata": {}
        },
        {
            "id": "0QA304043275#467604486_13L88808Q1931321776Q20",
            "marketId": "304043275",
            "label": "Over",
            "displayOdds": {
                "american": "−117",
                "decimal": "1.85",
                "fractional": "100/117"
            },
            "trueOdds": 1.85470086,
            "points": 1.5,
            "outcomeType": "Over",
            "participants": [
                {
                    "id": "17930",
                    "name": "DeMarcus Lawrence",
                    "type": "Player",
                    "seoIdentifier": "DeMarcus Lawrence",
                    "statistic": {
                        "prefix": "TCKPG",
                        "value": 1.6
                    },
                    "venueRole": "HomePlayer",
                    "isNationalTeam": false
                }
            ],
            "sortOrder": 1500,
            "tags": [
                "MainPointLine"
            ],
            "metadata": {}
        },
        {
            "id": "0QA304043275#467604505_13L88808Q1-825330146Q20",
            "marketId": "304043275",
            "label": "Under",
            "displayOdds": {
                "american": "−110",
                "decimal": "1.90",
                "fractional": "10/11"
            },
            "trueOdds": 1.90909091,
            "points": 1.5,
            "outcomeType": "Under",
            "participants": [
                {
                    "id": "17930",
                    "name": "DeMarcus Lawrence",
                    "type": "Player",
                    "seoIdentifier": "DeMarcus Lawrence",
                    "statistic": {
                        "prefix": "TCKPG",
                        "value": 1.6
                    },
                    "venueRole": "HomePlayer",
                    "isNationalTeam": false
                }
            ],
            "sortOrder": 1502,
            "tags": [
                "MainPointLine"
            ],
            "metadata": {}
        },
        {
            "id": "0QA304043306#467605468_13L88808Q1931321776Q20",
            "marketId": "304043306",
            "label": "Over",
            "displayOdds": {
                "american": "+105",
                "decimal": "2.05",
                "fractional": "21/20"
            },
            "trueOdds": 2.05,
            "points": 1.5,
            "outcomeType": "Over",
            "participants": [
                {
                    "id": "706561",
                    "name": "Kobie Turner",
                    "type": "Player",
                    "seoIdentifier": "Kobie Turner",
                    "statistic": {
                        "prefix": "TCKPG",
                        "value": 1.3
                    },
                    "venueRole": "AwayPlayer",
                    "isNationalTeam": false
                }
            ],
            "sortOrder": 1500,
            "tags": [
                "MainPointLine"
            ],
            "metadata": {}
        },
        {
            "id": "0QA304043306#467605475_13L88808Q1-825330146Q20",
            "marketId": "304043306",
            "label": "Under",
            "displayOdds": {
                "american": "−136",
                "decimal": "1.73",
                "fractional": "25/34"
            },
            "trueOdds": 1.73529412,
            "points": 1.5,
            "outcomeType": "Under",
            "participants": [
                {
                    "id": "706561",
                    "name": "Kobie Turner",
                    "type": "Player",
                    "seoIdentifier": "Kobie Turner",
                    "statistic": {
                        "prefix": "TCKPG",
                        "value": 1.3
                    },
                    "venueRole": "AwayPlayer",
                    "isNationalTeam": false
                }
            ],
            "sortOrder": 1502,
            "tags": [
                "MainPointLine"
            ],
            "metadata": {}
        },
        {
            "id": "0QA304043362#467603782_13L88808Q1-1302256359Q20",
            "marketId": "304043362",
            "label": "Over",
            "displayOdds": {
                "american": "+111",
                "decimal": "2.11",
                "fractional": "111/100"
            },
            "trueOdds": 2.11,
            "points": 4.5,
            "outcomeType": "Over",
            "participants": [
                {
                    "id": "485640",
                    "name": "Kamren Curl",
                    "type": "Player",
                    "seoIdentifier": "Kam Curl",
                    "statistic": {
                        "prefix": "TCKPG",
                        "value": 4.8
                    },
                    "venueRole": "AwayPlayer",
                    "isNationalTeam": false
                }
            ],
            "sortOrder": 4500,
            "tags": [
                "MainPointLine",
                "1stFavorite"
            ],
            "metadata": {}
        },
        {
            "id": "0QA304043362#467603878_13L88808Q1-1620814556Q20",
            "marketId": "304043362",
            "label": "Under",
            "displayOdds": {
                "american": "−143",
                "decimal": "1.69",
                "fractional": "100/143"
            },
            "trueOdds": 1.6993007,
            "points": 4.5,
            "outcomeType": "Under",
            "participants": [
                {
                    "id": "485640",
                    "name": "Kamren Curl",
                    "type": "Player",
                    "seoIdentifier": "Kam Curl",
                    "statistic": {
                        "prefix": "TCKPG",
                        "value": 4.8
                    },
                    "venueRole": "AwayPlayer",
                    "isNationalTeam": false
                }
            ],
            "sortOrder": 4502,
            "tags": [
                "MainPointLine",
                "1stFavorite"
            ],
            "metadata": {}
        },
        {
            "id": "0QA304043422#467605750_13L88808Q1-862046153Q20",
            "marketId": "304043422",
            "label": "Over",
            "displayOdds": {
                "american": "−147",
                "decimal": "1.68",
                "fractional": "100/147"
            },
            "trueOdds": 1.68027211,
            "points": 3.5,
            "outcomeType": "Over",
            "participants": [
                {
                    "id": "892746",
                    "name": "Nick Emmanwori",
                    "type": "Player",
                    "seoIdentifier": "Nick Emmanwori",
                    "statistic": {
                        "prefix": "TCKPG",
                        "value": 3.9
                    },
                    "venueRole": "HomePlayer",
                    "isNationalTeam": false
                }
            ],
            "sortOrder": 3500,
            "tags": [
                "MainPointLine",
                "2ndFavorite"
            ],
            "metadata": {}
        },
        {
            "id": "0QA304043422#467605751_13L88808Q1-1234571808Q20",
            "marketId": "304043422",
            "label": "Under",
            "displayOdds": {
                "american": "+114",
                "decimal": "2.14",
                "fractional": "57/50"
            },
            "trueOdds": 2.14,
            "points": 3.5,
            "outcomeType": "Under",
            "participants": [
                {
                    "id": "892746",
                    "name": "Nick Emmanwori",
                    "type": "Player",
                    "seoIdentifier": "Nick Emmanwori",
                    "statistic": {
                        "prefix": "TCKPG",
                        "value": 3.9
                    },
                    "venueRole": "HomePlayer",
                    "isNationalTeam": false
                }
            ],
            "sortOrder": 3502,
            "tags": [
                "MainPointLine",
                "2ndFavorite"
            ],
            "metadata": {}
        },
        {
            "id": "0QA304043477#468685428_13L88808Q1383535549Q20",
            "marketId": "304043477",
            "label": "Over",
            "displayOdds": {
                "american": "+121",
                "decimal": "2.21",
                "fractional": "121/100"
            },
            "trueOdds": 2.21,
            "points": 2.5,
            "outcomeType": "Over",
            "participants": [
                {
                    "id": "641001",
                    "name": "Coby Bryant",
                    "type": "Player",
                    "seoIdentifier": "Coby Bryant",
                    "statistic": {
                        "prefix": "TCKPG",
                        "value": 2.7
                    },
                    "venueRole": "HomePlayer",
                    "isNationalTeam": false
                }
            ],
            "sortOrder": 2500,
            "tags": [
                "MainPointLine"
            ],
            "metadata": {}
        },
        {
            "id": "0QA304043477#468685429_13L88808Q1801814857Q20",
            "marketId": "304043477",
            "label": "Under",
            "displayOdds": {
                "american": "−157",
                "decimal": "1.63",
                "fractional": "100/157"
            },
            "trueOdds": 1.63694268,
            "points": 2.5,
            "outcomeType": "Under",
            "participants": [
                {
                    "id": "641001",
                    "name": "Coby Bryant",
                    "type": "Player",
                    "seoIdentifier": "Coby Bryant",
                    "statistic": {
                        "prefix": "TCKPG",
                        "value": 2.7
                    },
                    "venueRole": "HomePlayer",
                    "isNationalTeam": false
                }
            ],
            "sortOrder": 2502,
            "tags": [
                "MainPointLine"
            ],
            "metadata": {}
        }
    ],
    "subscriptionPartials": {
        "events-49311580-45110647": {
            "entity": "events",
            "query": "$filter=leagueId eq '88808' AND clientMetadata/Subcategories/any(s: s/Id eq '18539')",
            "includeMarkets": "$filter=clientMetadata/subCategoryId eq '18539' AND tags/all(t: t ne 'SportcastBetBuilder')",
            "locale": "en"
        }
    }
}