[
  {
    "name": "Nolan Gorman",
    "line": 0.5,
    "over": {
      "american": "-175",
      "trueOdds": 1.57142858
    },
    "matchup": "NY Mets @ STL Cardinals",
    "gameTime": "2025-05-04T17:15:00.0000000Z",
    "under": {
      "american": "+125",
      "trueOdds": 2.25
    }
  },
  {
    "name": "Jose Barrero",
    "line": 0.5,
    "over": {
      "american": "-145",
      "trueOdds": 1.68965518
    },
    "matchup": "NY Mets @ STL Cardinals",
    "gameTime": "2025-05-04T17:15:00.0000000Z",
    "under": {
      "american": "+105",
      "trueOdds": 2.05
    }
  },
  {
    "name": "Luke Maile",
    "line": 0.5,
    "over": {
      "american": "-180",
      "trueOdds": 1.55555556
    },
    "matchup": "KC Royals @ BAL Orioles",
    "gameTime": "2025-05-04T17:35:00.0000000Z",
    "under": {
      "american": "+125",
      "trueOdds": 2.25
    }
  },
  {
    "name": "Trevor Larnach",
    "line": 0.5,
    "over": {
      "american": "-125",
      "trueOdds": 1.8
    },
    "matchup": "MIN Twins @ BOS Red Sox",
    "gameTime": "2025-05-04T17:35:00.0000000Z",
    "under": {
      "american": "-110",
      "trueOdds": 1.90909091
    }
  },
  {
    "name": "Travis Jankowski",
    "line": 0.5,
    "over": {
      "american": "-190",
      "trueOdds": 1.52631579
    },
    "matchup": "TB Rays @ NY Yankees",
    "gameTime": "2025-05-04T17:35:00.0000000Z",
    "under": {
      "american": "+135",
      "trueOdds": 2.35
    }
  },
  {
    "name": "Ben Rortvedt",
    "line": 0.5,
    "over": {
      "american": "-150",
      "trueOdds": 1.66666667
    },
    "matchup": "TB Rays @ NY Yankees",
    "gameTime": "2025-05-04T17:35:00.0000000Z",
    "under": {
      "american": "+110",
      "trueOdds": 2.1
    }
  },
  {
    "name": "Taylor Walls",
    "line": 0.5,
    "over": {
      "american": "-170",
      "trueOdds": 1.5882353
    },
    "matchup": "TB Rays @ NY Yankees",
    "gameTime": "2025-05-04T17:35:00.0000000Z",
    "under": {
      "american": "+120",
      "trueOdds": 2.2
    }
  },
  {
    "name": "Bo Naylor",
    "line": 0.5,
    "over": {
      "american": "-175",
      "trueOdds": 1.57142858
    },
    "matchup": "CLE Guardians @ TOR Blue Jays",
    "gameTime": "2025-05-04T17:37:00.0000000Z",
    "under": {
      "american": "+125",
      "trueOdds": 2.25
    }
  },
  {
    "name": "Kyle Stowers",
    "line": 0.5,
    "over": {
      "american": "-180",
      "trueOdds": 1.55555556
    },
    "matchup": "Athletics @ MIA Marlins",
    "gameTime": "2025-05-04T17:40:00.0000000Z",
    "under": {
      "american": "+130",
      "trueOdds": 2.3
    }
  },
  {
    "name": "Jose Herrera",
    "line": 0.5,
    "over": {
      "american": "-160",
      "trueOdds": 1.625
    },
    "matchup": "ARI Diamondbacks @ PHI Phillies",
    "gameTime": "2025-05-04T18:05:00.0000000Z",
    "under": {
      "american": "+115",
      "trueOdds": 2.15
    }
  },
  {
    "name": "Joshua Palacios",
    "line": 0.5,
    "over": {
      "american": "-140",
      "trueOdds": 1.71428572
    },
    "matchup": "HOU Astros @ CHI White Sox",
    "gameTime": "2025-05-04T18:10:00.0000000Z",
    "under": {
      "american": "+100",
      "trueOdds": 2
    }
  },
  {
    "name": "Josh Rojas",
    "line": 0.5,
    "over": {
      "american": "-155",
      "trueOdds": 1.6451613
    },
    "matchup": "HOU Astros @ CHI White Sox",
    "gameTime": "2025-05-04T18:10:00.0000000Z",
    "under": {
      "american": "+110",
      "trueOdds": 2.1
    }
  },
  {
    "name": "Dansby Swanson",
    "line": 0.5,
    "over": {
      "american": "-180",
      "trueOdds": 1.55555556
    },
    "matchup": "CHI Cubs @ MIL Brewers",
    "gameTime": "2025-05-04T18:10:00.0000000Z",
    "under": {
      "american": "+125",
      "trueOdds": 2.25
    }
  },
  {
    "name": "Miles Mastrobuoni",
    "line": 0.5,
    "over": {
      "american": "-185",
      "trueOdds": 1.54054055
    },
    "matchup": "SEA Mariners @ TEX Rangers",
    "gameTime": "2025-05-04T18:35:00.0000000Z",
    "under": {
      "american": "+130",
      "trueOdds": 2.3
    }
  },
  {
    "name": "Rowdy Tellez",
    "line": 0.5,
    "over": {
      "american": "-155",
      "trueOdds": 1.6451613
    },
    "matchup": "SEA Mariners @ TEX Rangers",
    "gameTime": "2025-05-04T18:35:00.0000000Z",
    "under": {
      "american": "+110",
      "trueOdds": 2.1
    }
  },
  {
    "name": "Leonardo Rivas",
    "line": 0.5,
    "over": {
      "american": "-140",
      "trueOdds": 1.71428572
    },
    "matchup": "SEA Mariners @ TEX Rangers",
    "gameTime": "2025-05-04T18:35:00.0000000Z",
    "under": {
      "american": "+100",
      "trueOdds": 2
    }
  },
  {
    "name": "Jacob Stallings",
    "line": 0.5,
    "over": {
      "american": "-185",
      "trueOdds": 1.54054055
    },
    "matchup": "COL Rockies @ SF Giants",
    "gameTime": "2025-05-04T20:05:00.0000000Z",
    "under": {
      "american": "+130",
      "trueOdds": 2.3
    }
  },
  {
    "name": "Mickey Moniak",
    "line": 0.5,
    "over": {
      "american": "-180",
      "trueOdds": 1.55555556
    },
    "matchup": "COL Rockies @ SF Giants",
    "gameTime": "2025-05-04T20:05:00.0000000Z",
    "under": {
      "american": "+125",
      "trueOdds": 2.25
    }
  },
  {
    "name": "Alan Trejo",
    "line": 0.5,
    "over": {
      "american": "-160",
      "trueOdds": 1.625
    },
    "matchup": "COL Rockies @ SF Giants",
    "gameTime": "2025-05-04T20:05:00.0000000Z",
    "under": {
      "american": "+115",
      "trueOdds": 2.15
    }
  },
  {
    "name": "Michael Toglia",
    "line": 0.5,
    "over": {
      "american": "-165",
      "trueOdds": 1.60606061
    },
    "matchup": "COL Rockies @ SF Giants",
    "gameTime": "2025-05-04T20:05:00.0000000Z",
    "under": {
      "american": "+115",
      "trueOdds": 2.15
    }
  },
  {
    "name": "Kyle Farmer",
    "line": 0.5,
    "over": {
      "american": "-190",
      "trueOdds": 1.52631579
    },
    "matchup": "COL Rockies @ SF Giants",
    "gameTime": "2025-05-04T20:05:00.0000000Z",
    "under": {
      "american": "+135",
      "trueOdds": 2.35
    }
  },
  {
    "name": "Tim Anderson",
    "line": 0.5,
    "over": {
      "american": "-180",
      "trueOdds": 1.55555556
    },
    "matchup": "DET Tigers @ LA Angels",
    "gameTime": "2025-05-04T20:07:00.0000000Z",
    "under": {
      "american": "+125",
      "trueOdds": 2.25
    }
  },
  {
    "name": "Kyren Paris",
    "line": 0.5,
    "over": {
      "american": "-165",
      "trueOdds": 1.60606061
    },
    "matchup": "DET Tigers @ LA Angels",
    "gameTime": "2025-05-04T20:07:00.0000000Z",
    "under": {
      "american": "+115",
      "trueOdds": 2.15
    }
  },
  {
    "name": "Blake Dunn",
    "line": 0.5,
    "over": {
      "american": "-150",
      "trueOdds": 1.66666667
    },
    "matchup": "WAS Nationals @ CIN Reds",
    "gameTime": "2025-05-04T20:10:00.0000000Z",
    "under": {
      "american": "+110",
      "trueOdds": 2.1
    }
  },
  {
    "name": "Alec Burleson",
    "line": 1.5,
    "over": {
      "american": "-130",
      "trueOdds": 1.76923077
    },
    "matchup": "NY Mets @ STL Cardinals",
    "gameTime": "2025-05-04T17:15:00.0000000Z",
    "under": {
      "american": "-110",
      "trueOdds": 1.90909091
    }
  },
  {
    "name": "Nolan Arenado",
    "line": 1.5,
    "over": {
      "american": "-110",
      "trueOdds": 1.90909091
    },
    "matchup": "NY Mets @ STL Cardinals",
    "gameTime": "2025-05-04T17:15:00.0000000Z",
    "under": {
      "american": "-130",
      "trueOdds": 1.76923077
    }
  },
  {
    "name": "Lars Nootbaar",
    "line": 1.5,
    "over": {
      "american": "-125",
      "trueOdds": 1.8
    },
    "matchup": "NY Mets @ STL Cardinals",
    "gameTime": "2025-05-04T17:15:00.0000000Z",
    "under": {
      "american": "-110",
      "trueOdds": 1.90909091
    }
  },
  {
    "name": "Willson Contreras",
    "line": 1.5,
    "over": {
      "american": "+105",
      "trueOdds": 2.05
    },
    "matchup": "NY Mets @ STL Cardinals",
    "gameTime": "2025-05-04T17:15:00.0000000Z",
    "under": {
      "american": "-145",
      "trueOdds": 1.68965518
    }
  },
  {
    "name": "Brendan Donovan",
    "line": 1.5,
    "over": {
      "american": "-135",
      "trueOdds": 1.74074075
    },
    "matchup": "NY Mets @ STL Cardinals",
    "gameTime": "2025-05-04T17:15:00.0000000Z",
    "under": {
      "american": "-105",
      "trueOdds": 1.95238096
    }
  },
  {
    "name": "Pedro Pages",
    "line": 1.5,
    "over": {
      "american": "+130",
      "trueOdds": 2.3
    },
    "matchup": "NY Mets @ STL Cardinals",
    "gameTime": "2025-05-04T17:15:00.0000000Z",
    "under": {
      "american": "-185",
      "trueOdds": 1.54054055
    }
  },
  {
    "name": "Victor Scott II",
    "line": 1.5,
    "over": {
      "american": "+125",
      "trueOdds": 2.25
    },
    "matchup": "NY Mets @ STL Cardinals",
    "gameTime": "2025-05-04T17:15:00.0000000Z",
    "under": {
      "american": "-180",
      "trueOdds": 1.55555556
    }
  },
  {
    "name": "Jose Azocar",
    "line": 1.5,
    "over": {
      "american": "+120",
      "trueOdds": 2.2
    },
    "matchup": "NY Mets @ STL Cardinals",
    "gameTime": "2025-05-04T17:15:00.0000000Z",
    "under": {
      "american": "-170",
      "trueOdds": 1.5882353
    }
  },
  {
    "name": "Jeff McNeil",
    "line": 1.5,
    "over": {
      "american": "+110",
      "trueOdds": 2.1
    },
    "matchup": "NY Mets @ STL Cardinals",
    "gameTime": "2025-05-04T17:15:00.0000000Z",
    "under": {
      "american": "-150",
      "trueOdds": 1.66666667
    }
  },
  {
    "name": "Francisco Lindor",
    "line": 1.5,
    "over": {
      "american": "-170",
      "trueOdds": 1.5882353
    },
    "matchup": "NY Mets @ STL Cardinals",
    "gameTime": "2025-05-04T17:15:00.0000000Z",
    "under": {
      "american": "+120",
      "trueOdds": 2.2
    }
  },
  {
    "name": "Luisangel Acuna",
    "line": 1.5,
    "over": {
      "american": "+100",
      "trueOdds": 2
    },
    "matchup": "NY Mets @ STL Cardinals",
    "gameTime": "2025-05-04T17:15:00.0000000Z",
    "under": {
      "american": "-140",
      "trueOdds": 1.71428572
    }
  },
  {
    "name": "Juan Soto",
    "line": 1.5,
    "over": {
      "american": "-145",
      "trueOdds": 1.68965518
    },
    "matchup": "NY Mets @ STL Cardinals",
    "gameTime": "2025-05-04T17:15:00.0000000Z",
    "under": {
      "american": "+105",
      "trueOdds": 2.05
    }
  },
  {
    "name": "Luis Torrens",
    "line": 1.5,
    "over": {
      "american": "-105",
      "trueOdds": 1.95238096
    },
    "matchup": "NY Mets @ STL Cardinals",
    "gameTime": "2025-05-04T17:15:00.0000000Z",
    "under": {
      "american": "-135",
      "trueOdds": 1.74074075
    }
  },
  {
    "name": "Brandon Nimmo",
    "line": 1.5,
    "over": {
      "american": "-125",
      "trueOdds": 1.8
    },
    "matchup": "NY Mets @ STL Cardinals",
    "gameTime": "2025-05-04T17:15:00.0000000Z",
    "under": {
      "american": "-115",
      "trueOdds": 1.86956522
    }
  },
  {
    "name": "Pete Alonso",
    "line": 1.5,
    "over": {
      "american": "-145",
      "trueOdds": 1.68965518
    },
    "matchup": "NY Mets @ STL Cardinals",
    "gameTime": "2025-05-04T17:15:00.0000000Z",
    "under": {
      "american": "+105",
      "trueOdds": 2.05
    }
  },
  {
    "name": "Jesse Winker",
    "line": 1.5,
    "over": {
      "american": "+115",
      "trueOdds": 2.15
    },
    "matchup": "NY Mets @ STL Cardinals",
    "gameTime": "2025-05-04T17:15:00.0000000Z",
    "under": {
      "american": "-165",
      "trueOdds": 1.60606061
    }
  },
  {
    "name": "Maverick Handley",
    "line": 1.5,
    "over": {
      "american": "+125",
      "trueOdds": 2.25
    },
    "matchup": "KC Royals @ BAL Orioles",
    "gameTime": "2025-05-04T17:35:00.0000000Z",
    "under": {
      "american": "-180",
      "trueOdds": 1.55555556
    }
  },
  {
    "name": "Hunter Renfroe",
    "line": 1.5,
    "over": {
      "american": "+110",
      "trueOdds": 2.1
    },
    "matchup": "KC Royals @ BAL Orioles",
    "gameTime": "2025-05-04T17:35:00.0000000Z",
    "under": {
      "american": "-155",
      "trueOdds": 1.6451613
    }
  },
  {
    "name": "Maikel Garcia",
    "line": 1.5,
    "over": {
      "american": "-150",
      "trueOdds": 1.66666667
    },
    "matchup": "KC Royals @ BAL Orioles",
    "gameTime": "2025-05-04T17:35:00.0000000Z",
    "under": {
      "american": "+105",
      "trueOdds": 2.05
    }
  },
  {
    "name": "Michael Massey",
    "line": 1.5,
    "over": {
      "american": "-115",
      "trueOdds": 1.86956522
    },
    "matchup": "KC Royals @ BAL Orioles",
    "gameTime": "2025-05-04T17:35:00.0000000Z",
    "under": {
      "american": "-125",
      "trueOdds": 1.8
    }
  },
  {
    "name": "Drew Waters",
    "line": 1.5,
    "over": {
      "american": "+110",
      "trueOdds": 2.1
    },
    "matchup": "KC Royals @ BAL Orioles",
    "gameTime": "2025-05-04T17:35:00.0000000Z",
    "under": {
      "american": "-160",
      "trueOdds": 1.625
    }
  },
  {
    "name": "Salvador Perez",
    "line": 1.5,
    "over": {
      "american": "-155",
      "trueOdds": 1.6451613
    },
    "matchup": "KC Royals @ BAL Orioles",
    "gameTime": "2025-05-04T17:35:00.0000000Z",
    "under": {
      "american": "+110",
      "trueOdds": 2.1
    }
  },
  {
    "name": "Jonathan India",
    "line": 1.5,
    "over": {
      "american": "-145",
      "trueOdds": 1.68965518
    },
    "matchup": "KC Royals @ BAL Orioles",
    "gameTime": "2025-05-04T17:35:00.0000000Z",
    "under": {
      "american": "+100",
      "trueOdds": 2
    }
  },
  {
    "name": "Vinnie Pasquantino",
    "line": 1.5,
    "over": {
      "american": "-135",
      "trueOdds": 1.74074075
    },
    "matchup": "KC Royals @ BAL Orioles",
    "gameTime": "2025-05-04T17:35:00.0000000Z",
    "under": {
      "american": "-105",
      "trueOdds": 1.95238096
    }
  },
  {
    "name": "Cedric Mullins",
    "line": 1.5,
    "over": {
      "american": "-125",
      "trueOdds": 1.8
    },
    "matchup": "KC Royals @ BAL Orioles",
    "gameTime": "2025-05-04T17:35:00.0000000Z",
    "under": {
      "american": "-110",
      "trueOdds": 1.90909091
    }
  },
  {
    "name": "Ryan O'Hearn",
    "line": 1.5,
    "over": {
      "american": "-125",
      "trueOdds": 1.8
    },
    "matchup": "KC Royals @ BAL Orioles",
    "gameTime": "2025-05-04T17:35:00.0000000Z",
    "under": {
      "american": "-110",
      "trueOdds": 1.90909091
    }
  },
  {
    "name": "Heston Kjerstad",
    "line": 1.5,
    "over": {
      "american": "-105",
      "trueOdds": 1.95238096
    },
    "matchup": "KC Royals @ BAL Orioles",
    "gameTime": "2025-05-04T17:35:00.0000000Z",
    "under": {
      "american": "-135",
      "trueOdds": 1.74074075
    }
  },
  {
    "name": "Coby Mayo",
    "line": 1.5,
    "over": {
      "american": "+105",
      "trueOdds": 2.05
    },
    "matchup": "KC Royals @ BAL Orioles",
    "gameTime": "2025-05-04T17:35:00.0000000Z",
    "under": {
      "american": "-150",
      "trueOdds": 1.66666667
    }
  },
  {
    "name": "Gunnar Henderson",
    "line": 1.5,
    "over": {
      "american": "-160",
      "trueOdds": 1.625
    },
    "matchup": "KC Royals @ BAL Orioles",
    "gameTime": "2025-05-04T17:35:00.0000000Z",
    "under": {
      "american": "+110",
      "trueOdds": 2.1
    }
  },
  {
    "name": "Adley Rutschman",
    "line": 1.5,
    "over": {
      "american": "-130",
      "trueOdds": 1.76923077
    },
    "matchup": "KC Royals @ BAL Orioles",
    "gameTime": "2025-05-04T17:35:00.0000000Z",
    "under": {
      "american": "-110",
      "trueOdds": 1.90909091
    }
  },
  {
    "name": "Ryan Mountcastle",
    "line": 1.5,
    "over": {
      "american": "-150",
      "trueOdds": 1.66666667
    },
    "matchup": "KC Royals @ BAL Orioles",
    "gameTime": "2025-05-04T17:35:00.0000000Z",
    "under": {
      "american": "+110",
      "trueOdds": 2.1
    }
  },
  {
    "name": "Jackson Holliday",
    "line": 1.5,
    "over": {
      "american": "-115",
      "trueOdds": 1.86956522
    },
    "matchup": "KC Royals @ BAL Orioles",
    "gameTime": "2025-05-04T17:35:00.0000000Z",
    "under": {
      "american": "-125",
      "trueOdds": 1.8
    }
  },
  {
    "name": "Jonah Bride",
    "line": 1.5,
    "over": {
      "american": "+125",
      "trueOdds": 2.25
    },
    "matchup": "MIN Twins @ BOS Red Sox",
    "gameTime": "2025-05-04T17:35:00.0000000Z",
    "under": {
      "american": "-180",
      "trueOdds": 1.55555556
    }
  },
  {
    "name": "Harrison Bader",
    "line": 1.5,
    "over": {
      "american": "+100",
      "trueOdds": 2
    },
    "matchup": "MIN Twins @ BOS Red Sox",
    "gameTime": "2025-05-04T17:35:00.0000000Z",
    "under": {
      "american": "-140",
      "trueOdds": 1.71428572
    }
  },
  {
    "name": "Christian Vazquez",
    "line": 1.5,
    "over": {
      "american": "+130",
      "trueOdds": 2.3
    },
    "matchup": "MIN Twins @ BOS Red Sox",
    "gameTime": "2025-05-04T17:35:00.0000000Z",
    "under": {
      "american": "-185",
      "trueOdds": 1.54054055
    }
  },
  {
    "name": "Ryan Jeffers",
    "line": 1.5,
    "over": {
      "american": "-110",
      "trueOdds": 1.90909091
    },
    "matchup": "MIN Twins @ BOS Red Sox",
    "gameTime": "2025-05-04T17:35:00.0000000Z",
    "under": {
      "american": "-130",
      "trueOdds": 1.76923077
    }
  },
  {
    "name": "Kristian Campbell",
    "line": 1.5,
    "over": {
      "american": "-140",
      "trueOdds": 1.71428572
    },
    "matchup": "MIN Twins @ BOS Red Sox",
    "gameTime": "2025-05-04T17:35:00.0000000Z",
    "under": {
      "american": "+100",
      "trueOdds": 2
    }
  },
  {
    "name": "Byron Buxton",
    "line": 1.5,
    "over": {
      "american": "-125",
      "trueOdds": 1.8
    },
    "matchup": "MIN Twins @ BOS Red Sox",
    "gameTime": "2025-05-04T17:35:00.0000000Z",
    "under": {
      "american": "-115",
      "trueOdds": 1.86956522
    }
  },
  {
    "name": "Carlos Correa",
    "line": 1.5,
    "over": {
      "american": "-125",
      "trueOdds": 1.8
    },
    "matchup": "MIN Twins @ BOS Red Sox",
    "gameTime": "2025-05-04T17:35:00.0000000Z",
    "under": {
      "american": "-115",
      "trueOdds": 1.86956522
    }
  },
  {
    "name": "Ceddanne Rafaela",
    "line": 1.5,
    "over": {
      "american": "-125",
      "trueOdds": 1.8
    },
    "matchup": "MIN Twins @ BOS Red Sox",
    "gameTime": "2025-05-04T17:35:00.0000000Z",
    "under": {
      "american": "-115",
      "trueOdds": 1.86956522
    }
  },
  {
    "name": "Romy Gonzalez",
    "line": 1.5,
    "over": {
      "american": "-135",
      "trueOdds": 1.74074075
    },
    "matchup": "MIN Twins @ BOS Red Sox",
    "gameTime": "2025-05-04T17:35:00.0000000Z",
    "under": {
      "american": "-105",
      "trueOdds": 1.95238096
    }
  },
  {
    "name": "Ty France",
    "line": 1.5,
    "over": {
      "american": "-120",
      "trueOdds": 1.83333334
    },
    "matchup": "MIN Twins @ BOS Red Sox",
    "gameTime": "2025-05-04T17:35:00.0000000Z",
    "under": {
      "american": "-120",
      "trueOdds": 1.83333334
    }
  },
  {
    "name": "Wilyer Abreu",
    "line": 1.5,
    "over": {
      "american": "-150",
      "trueOdds": 1.66666667
    },
    "matchup": "MIN Twins @ BOS Red Sox",
    "gameTime": "2025-05-04T17:35:00.0000000Z",
    "under": {
      "american": "+105",
      "trueOdds": 2.05
    }
  },
  {
    "name": "Carlos Narvaez",
    "line": 1.5,
    "over": {
      "american": "+100",
      "trueOdds": 2
    },
    "matchup": "MIN Twins @ BOS Red Sox",
    "gameTime": "2025-05-04T17:35:00.0000000Z",
    "under": {
      "american": "-145",
      "trueOdds": 1.68965518
    }
  },
  {
    "name": "David Hamilton",
    "line": 1.5,
    "over": {
      "american": "-110",
      "trueOdds": 1.90909091
    },
    "matchup": "MIN Twins @ BOS Red Sox",
    "gameTime": "2025-05-04T17:35:00.0000000Z",
    "under": {
      "american": "-125",
      "trueOdds": 1.8
    }
  },
  {
    "name": "Brooks Lee",
    "line": 1.5,
    "over": {
      "american": "+115",
      "trueOdds": 2.15
    },
    "matchup": "MIN Twins @ BOS Red Sox",
    "gameTime": "2025-05-04T17:35:00.0000000Z",
    "under": {
      "american": "-160",
      "trueOdds": 1.625
    }
  },
  {
    "name": "Chandler Simpson",
    "line": 1.5,
    "over": {
      "american": "-130",
      "trueOdds": 1.76923077
    },
    "matchup": "TB Rays @ NY Yankees",
    "gameTime": "2025-05-04T17:35:00.0000000Z",
    "under": {
      "american": "-105",
      "trueOdds": 1.95238096
    }
  },
  {
    "name": "Brandon Lowe",
    "line": 1.5,
    "over": {
      "american": "-105",
      "trueOdds": 1.95238096
    },
    "matchup": "TB Rays @ NY Yankees",
    "gameTime": "2025-05-04T17:35:00.0000000Z",
    "under": {
      "american": "-135",
      "trueOdds": 1.74074075
    }
  },
  {
    "name": "Kameron Misner",
    "line": 1.5,
    "over": {
      "american": "+125",
      "trueOdds": 2.25
    },
    "matchup": "TB Rays @ NY Yankees",
    "gameTime": "2025-05-04T17:35:00.0000000Z",
    "under": {
      "american": "-175",
      "trueOdds": 1.57142858
    }
  },
  {
    "name": "Pablo Reyes",
    "line": 1.5,
    "over": {
      "american": "+115",
      "trueOdds": 2.15
    },
    "matchup": "TB Rays @ NY Yankees",
    "gameTime": "2025-05-04T17:35:00.0000000Z",
    "under": {
      "american": "-165",
      "trueOdds": 1.60606061
    }
  },
  {
    "name": "Oswald Peraza",
    "line": 1.5,
    "over": {
      "american": "+125",
      "trueOdds": 2.25
    },
    "matchup": "TB Rays @ NY Yankees",
    "gameTime": "2025-05-04T17:35:00.0000000Z",
    "under": {
      "american": "-180",
      "trueOdds": 1.55555556
    }
  },
  {
    "name": "Jasson Dominguez",
    "line": 1.5,
    "over": {
      "american": "-110",
      "trueOdds": 1.90909091
    },
    "matchup": "TB Rays @ NY Yankees",
    "gameTime": "2025-05-04T17:35:00.0000000Z",
    "under": {
      "american": "-125",
      "trueOdds": 1.8
    }
  },
  {
    "name": "Curtis Mead",
    "line": 1.5,
    "over": {
      "american": "+110",
      "trueOdds": 2.1
    },
    "matchup": "TB Rays @ NY Yankees",
    "gameTime": "2025-05-04T17:35:00.0000000Z",
    "under": {
      "american": "-155",
      "trueOdds": 1.6451613
    }
  },
  {
    "name": "J.C. Escarra",
    "line": 1.5,
    "over": {
      "american": "+130",
      "trueOdds": 2.3
    },
    "matchup": "TB Rays @ NY Yankees",
    "gameTime": "2025-05-04T17:35:00.0000000Z",
    "under": {
      "american": "-185",
      "trueOdds": 1.54054055
    }
  },
  {
    "name": "Paul Goldschmidt",
    "line": 1.5,
    "over": {
      "american": "-155",
      "trueOdds": 1.6451613
    },
    "matchup": "TB Rays @ NY Yankees",
    "gameTime": "2025-05-04T17:35:00.0000000Z",
    "under": {
      "american": "+110",
      "trueOdds": 2.1
    }
  },
  {
    "name": "Trent Grisham",
    "line": 1.5,
    "over": {
      "american": "-125",
      "trueOdds": 1.8
    },
    "matchup": "TB Rays @ NY Yankees",
    "gameTime": "2025-05-04T17:35:00.0000000Z",
    "under": {
      "american": "-115",
      "trueOdds": 1.86956522
    }
  },
  {
    "name": "Oswaldo Cabrera",
    "line": 1.5,
    "over": {
      "american": "+120",
      "trueOdds": 2.2
    },
    "matchup": "TB Rays @ NY Yankees",
    "gameTime": "2025-05-04T17:35:00.0000000Z",
    "under": {
      "american": "-165",
      "trueOdds": 1.60606061
    }
  },
  {
    "name": "Yandy Diaz",
    "line": 1.5,
    "over": {
      "american": "-140",
      "trueOdds": 1.71428572
    },
    "matchup": "TB Rays @ NY Yankees",
    "gameTime": "2025-05-04T17:35:00.0000000Z",
    "under": {
      "american": "+100",
      "trueOdds": 2
    }
  },
  {
    "name": "Cody Bellinger",
    "line": 1.5,
    "over": {
      "american": "-115",
      "trueOdds": 1.86956522
    },
    "matchup": "TB Rays @ NY Yankees",
    "gameTime": "2025-05-04T17:35:00.0000000Z",
    "under": {
      "american": "-125",
      "trueOdds": 1.8
    }
  },
  {
    "name": "Jonathan Aranda",
    "line": 1.5,
    "over": {
      "american": "+100",
      "trueOdds": 2
    },
    "matchup": "TB Rays @ NY Yankees",
    "gameTime": "2025-05-04T17:35:00.0000000Z",
    "under": {
      "american": "-140",
      "trueOdds": 1.71428572
    }
  },
  {
    "name": "Tommy Pham",
    "line": 1.5,
    "over": {
      "american": "-125",
      "trueOdds": 1.8
    },
    "matchup": "SD Padres @ PIT Pirates",
    "gameTime": "2025-05-04T17:35:00.0000000Z",
    "under": {
      "american": "-115",
      "trueOdds": 1.86956522
    }
  },
  {
    "name": "Henry Davis",
    "line": 1.5,
    "over": {
      "american": "+115",
      "trueOdds": 2.15
    },
    "matchup": "SD Padres @ PIT Pirates",
    "gameTime": "2025-05-04T17:35:00.0000000Z",
    "under": {
      "american": "-165",
      "trueOdds": 1.60606061
    }
  },
  {
    "name": "Enmanuel Valdez",
    "line": 1.5,
    "over": {
      "american": "-115",
      "trueOdds": 1.86956522
    },
    "matchup": "SD Padres @ PIT Pirates",
    "gameTime": "2025-05-04T17:35:00.0000000Z",
    "under": {
      "american": "-125",
      "trueOdds": 1.8
    }
  },
  {
    "name": "Joey Bart",
    "line": 1.5,
    "over": {
      "american": "-115",
      "trueOdds": 1.86956522
    },
    "matchup": "SD Padres @ PIT Pirates",
    "gameTime": "2025-05-04T17:35:00.0000000Z",
    "under": {
      "american": "-120",
      "trueOdds": 1.83333334
    }
  },
  {
    "name": "Ke'Bryan Hayes",
    "line": 1.5,
    "over": {
      "american": "-130",
      "trueOdds": 1.76923077
    },
    "matchup": "SD Padres @ PIT Pirates",
    "gameTime": "2025-05-04T17:35:00.0000000Z",
    "under": {
      "american": "-105",
      "trueOdds": 1.95238096
    }
  },
  {
    "name": "Adam Frazier",
    "line": 1.5,
    "over": {
      "american": "+105",
      "trueOdds": 2.05
    },
    "matchup": "SD Padres @ PIT Pirates",
    "gameTime": "2025-05-04T17:35:00.0000000Z",
    "under": {
      "american": "-150",
      "trueOdds": 1.66666667
    }
  },
  {
    "name": "Oneil Cruz",
    "line": 1.5,
    "over": {
      "american": "-160",
      "trueOdds": 1.625
    },
    "matchup": "SD Padres @ PIT Pirates",
    "gameTime": "2025-05-04T17:35:00.0000000Z",
    "under": {
      "american": "+110",
      "trueOdds": 2.1
    }
  },
  {
    "name": "Jared Triolo",
    "line": 1.5,
    "over": {
      "american": "+100",
      "trueOdds": 2
    },
    "matchup": "SD Padres @ PIT Pirates",
    "gameTime": "2025-05-04T17:35:00.0000000Z",
    "under": {
      "american": "-145",
      "trueOdds": 1.68965518
    }
  },
  {
    "name": "Bryan Reynolds",
    "line": 1.5,
    "over": {
      "american": "-140",
      "trueOdds": 1.71428572
    },
    "matchup": "SD Padres @ PIT Pirates",
    "gameTime": "2025-05-04T17:35:00.0000000Z",
    "under": {
      "american": "+100",
      "trueOdds": 2
    }
  },
  {
    "name": "Elias Diaz",
    "line": 1.5,
    "over": {
      "american": "+110",
      "trueOdds": 2.1
    },
    "matchup": "SD Padres @ PIT Pirates",
    "gameTime": "2025-05-04T17:35:00.0000000Z",
    "under": {
      "american": "-155",
      "trueOdds": 1.6451613
    }
  },
  {
    "name": "Jose Iglesias",
    "line": 1.5,
    "over": {
      "american": "-110",
      "trueOdds": 1.90909091
    },
    "matchup": "SD Padres @ PIT Pirates",
    "gameTime": "2025-05-04T17:35:00.0000000Z",
    "under": {
      "american": "-130",
      "trueOdds": 1.76923077
    }
  },
  {
    "name": "Manny Machado",
    "line": 1.5,
    "over": {
      "american": "-155",
      "trueOdds": 1.6451613
    },
    "matchup": "SD Padres @ PIT Pirates",
    "gameTime": "2025-05-04T17:35:00.0000000Z",
    "under": {
      "american": "+110",
      "trueOdds": 2.1
    }
  },
  {
    "name": "Oscar Gonzalez",
    "line": 1.5,
    "over": {
      "american": "-120",
      "trueOdds": 1.83333334
    },
    "matchup": "SD Padres @ PIT Pirates",
    "gameTime": "2025-05-04T17:35:00.0000000Z",
    "under": {
      "american": "-120",
      "trueOdds": 1.83333334
    }
  },
  {
    "name": "Luis Arraez",
    "line": 1.5,
    "over": {
      "american": "-150",
      "trueOdds": 1.66666667
    },
    "matchup": "SD Padres @ PIT Pirates",
    "gameTime": "2025-05-04T17:35:00.0000000Z",
    "under": {
      "american": "+105",
      "trueOdds": 2.05
    }
  },
  {
    "name": "Brandon Lockridge",
    "line": 1.5,
    "over": {
      "american": "+115",
      "trueOdds": 2.15
    },
    "matchup": "SD Padres @ PIT Pirates",
    "gameTime": "2025-05-04T17:35:00.0000000Z",
    "under": {
      "american": "-160",
      "trueOdds": 1.625
    }
  },
  {
    "name": "Xander Bogaerts",
    "line": 1.5,
    "over": {
      "american": "-125",
      "trueOdds": 1.8
    },
    "matchup": "SD Padres @ PIT Pirates",
    "gameTime": "2025-05-04T17:35:00.0000000Z",
    "under": {
      "american": "-110",
      "trueOdds": 1.90909091
    }
  },
  {
    "name": "Luis Campusano",
    "line": 1.5,
    "over": {
      "american": "+100",
      "trueOdds": 2
    },
    "matchup": "SD Padres @ PIT Pirates",
    "gameTime": "2025-05-04T17:35:00.0000000Z",
    "under": {
      "american": "-140",
      "trueOdds": 1.71428572
    }
  },
  {
    "name": "Jose Ramirez",
    "line": 1.5,
    "over": {
      "american": "-145",
      "trueOdds": 1.68965518
    },
    "matchup": "CLE Guardians @ TOR Blue Jays",
    "gameTime": "2025-05-04T17:37:00.0000000Z",
    "under": {
      "american": "+100",
      "trueOdds": 2
    }
  },
  {
    "name": "Alan Roden",
    "line": 1.5,
    "over": {
      "american": "+110",
      "trueOdds": 2.1
    },
    "matchup": "CLE Guardians @ TOR Blue Jays",
    "gameTime": "2025-05-04T17:37:00.0000000Z",
    "under": {
      "american": "-155",
      "trueOdds": 1.6451613
    }
  },
  {
    "name": "Alejandro Kirk",
    "line": 1.5,
    "over": {
      "american": "-120",
      "trueOdds": 1.83333334
    },
    "matchup": "CLE Guardians @ TOR Blue Jays",
    "gameTime": "2025-05-04T17:37:00.0000000Z",
    "under": {
      "american": "-120",
      "trueOdds": 1.83333334
    }
  },
  {
    "name": "Andres Gimenez",
    "line": 1.5,
    "over": {
      "american": "+110",
      "trueOdds": 2.1
    },
    "matchup": "CLE Guardians @ TOR Blue Jays",
    "gameTime": "2025-05-04T17:37:00.0000000Z",
    "under": {
      "american": "-155",
      "trueOdds": 1.6451613
    }
  },
  {
    "name": "George Springer",
    "line": 1.5,
    "over": {
      "american": "-105",
      "trueOdds": 1.95238096
    },
    "matchup": "CLE Guardians @ TOR Blue Jays",
    "gameTime": "2025-05-04T17:37:00.0000000Z",
    "under": {
      "american": "-135",
      "trueOdds": 1.74074075
    }
  },
  {
    "name": "Addison Barger",
    "line": 1.5,
    "over": {
      "american": "+110",
      "trueOdds": 2.1
    },
    "matchup": "CLE Guardians @ TOR Blue Jays",
    "gameTime": "2025-05-04T17:37:00.0000000Z",
    "under": {
      "american": "-160",
      "trueOdds": 1.625
    }
  },
  {
    "name": "Anthony Santander",
    "line": 1.5,
    "over": {
      "american": "-115",
      "trueOdds": 1.86956522
    },
    "matchup": "CLE Guardians @ TOR Blue Jays",
    "gameTime": "2025-05-04T17:37:00.0000000Z",
    "under": {
      "american": "-125",
      "trueOdds": 1.8
    }
  },
  {
    "name": "Steven Kwan",
    "line": 1.5,
    "over": {
      "american": "-150",
      "trueOdds": 1.66666667
    },
    "matchup": "CLE Guardians @ TOR Blue Jays",
    "gameTime": "2025-05-04T17:37:00.0000000Z",
    "under": {
      "american": "+105",
      "trueOdds": 2.05
    }
  },
  {
    "name": "Bo Bichette",
    "line": 1.5,
    "over": {
      "american": "-165",
      "trueOdds": 1.60606061
    },
    "matchup": "CLE Guardians @ TOR Blue Jays",
    "gameTime": "2025-05-04T17:37:00.0000000Z",
    "under": {
      "american": "+120",
      "trueOdds": 2.2
    }
  },
  {
    "name": "Vladimir Guerrero Jr.",
    "line": 1.5,
    "over": {
      "american": "-140",
      "trueOdds": 1.71428572
    },
    "matchup": "CLE Guardians @ TOR Blue Jays",
    "gameTime": "2025-05-04T17:37:00.0000000Z",
    "under": {
      "american": "+100",
      "trueOdds": 2
    }
  },
  {
    "name": "Nolan Jones",
    "line": 1.5,
    "over": {
      "american": "+105",
      "trueOdds": 2.05
    },
    "matchup": "CLE Guardians @ TOR Blue Jays",
    "gameTime": "2025-05-04T17:37:00.0000000Z",
    "under": {
      "american": "-145",
      "trueOdds": 1.68965518
    }
  },
  {
    "name": "Carlos Santana",
    "line": 1.5,
    "over": {
      "american": "-105",
      "trueOdds": 1.95238096
    },
    "matchup": "CLE Guardians @ TOR Blue Jays",
    "gameTime": "2025-05-04T17:37:00.0000000Z",
    "under": {
      "american": "-135",
      "trueOdds": 1.74074075
    }
  },
  {
    "name": "Kyle Manzardo",
    "line": 1.5,
    "over": {
      "american": "+100",
      "trueOdds": 2
    },
    "matchup": "CLE Guardians @ TOR Blue Jays",
    "gameTime": "2025-05-04T17:37:00.0000000Z",
    "under": {
      "american": "-140",
      "trueOdds": 1.71428572
    }
  },
  {
    "name": "Gabriel Arias",
    "line": 1.5,
    "over": {
      "american": "+115",
      "trueOdds": 2.15
    },
    "matchup": "CLE Guardians @ TOR Blue Jays",
    "gameTime": "2025-05-04T17:37:00.0000000Z",
    "under": {
      "american": "-165",
      "trueOdds": 1.60606061
    }
  },
  {
    "name": "Nathan Lukes",
    "line": 1.5,
    "over": {
      "american": "+110",
      "trueOdds": 2.1
    },
    "matchup": "CLE Guardians @ TOR Blue Jays",
    "gameTime": "2025-05-04T17:37:00.0000000Z",
    "under": {
      "american": "-155",
      "trueOdds": 1.6451613
    }
  },
  {
    "name": "Daniel Schneemann",
    "line": 1.5,
    "over": {
      "american": "+130",
      "trueOdds": 2.3
    },
    "matchup": "CLE Guardians @ TOR Blue Jays",
    "gameTime": "2025-05-04T17:37:00.0000000Z",
    "under": {
      "american": "-185",
      "trueOdds": 1.54054055
    }
  },
  {
    "name": "Angel Martinez",
    "line": 1.5,
    "over": {
      "american": "+115",
      "trueOdds": 2.15
    },
    "matchup": "CLE Guardians @ TOR Blue Jays",
    "gameTime": "2025-05-04T17:37:00.0000000Z",
    "under": {
      "american": "-165",
      "trueOdds": 1.60606061
    }
  },
  {
    "name": "Gio Urshela",
    "line": 1.5,
    "over": {
      "american": "+100",
      "trueOdds": 2
    },
    "matchup": "Athletics @ MIA Marlins",
    "gameTime": "2025-05-04T17:40:00.0000000Z",
    "under": {
      "american": "-140",
      "trueOdds": 1.71428572
    }
  },
  {
    "name": "Luis Urias",
    "line": 1.5,
    "over": {
      "american": "+115",
      "trueOdds": 2.15
    },
    "matchup": "Athletics @ MIA Marlins",
    "gameTime": "2025-05-04T17:40:00.0000000Z",
    "under": {
      "american": "-160",
      "trueOdds": 1.625
    }
  },
  {
    "name": "Brent Rooker",
    "line": 1.5,
    "over": {
      "american": "-120",
      "trueOdds": 1.83333334
    },
    "matchup": "Athletics @ MIA Marlins",
    "gameTime": "2025-05-04T17:40:00.0000000Z",
    "under": {
      "american": "-115",
      "trueOdds": 1.86956522
    }
  },
  {
    "name": "JJ Bleday",
    "line": 1.5,
    "over": {
      "american": "-115",
      "trueOdds": 1.86956522
    },
    "matchup": "Athletics @ MIA Marlins",
    "gameTime": "2025-05-04T17:40:00.0000000Z",
    "under": {
      "american": "-120",
      "trueOdds": 1.83333334
    }
  },
  {
    "name": "Nick Kurtz",
    "line": 1.5,
    "over": {
      "american": "+105",
      "trueOdds": 2.05
    },
    "matchup": "Athletics @ MIA Marlins",
    "gameTime": "2025-05-04T17:40:00.0000000Z",
    "under": {
      "american": "-145",
      "trueOdds": 1.68965518
    }
  },
  {
    "name": "Lawrence Butler",
    "line": 1.5,
    "over": {
      "american": "-130",
      "trueOdds": 1.76923077
    },
    "matchup": "Athletics @ MIA Marlins",
    "gameTime": "2025-05-04T17:40:00.0000000Z",
    "under": {
      "american": "-110",
      "trueOdds": 1.90909091
    }
  },
  {
    "name": "Jacob Wilson",
    "line": 1.5,
    "over": {
      "american": "-130",
      "trueOdds": 1.76923077
    },
    "matchup": "Athletics @ MIA Marlins",
    "gameTime": "2025-05-04T17:40:00.0000000Z",
    "under": {
      "american": "-105",
      "trueOdds": 1.95238096
    }
  },
  {
    "name": "Miguel Andujar",
    "line": 1.5,
    "over": {
      "american": "-130",
      "trueOdds": 1.76923077
    },
    "matchup": "Athletics @ MIA Marlins",
    "gameTime": "2025-05-04T17:40:00.0000000Z",
    "under": {
      "american": "-110",
      "trueOdds": 1.90909091
    }
  },
  {
    "name": "Jhonny Pereda",
    "line": 1.5,
    "over": {
      "american": "+130",
      "trueOdds": 2.3
    },
    "matchup": "Athletics @ MIA Marlins",
    "gameTime": "2025-05-04T17:40:00.0000000Z",
    "under": {
      "american": "-180",
      "trueOdds": 1.55555556
    }
  },
  {
    "name": "Nick Fortes",
    "line": 1.5,
    "over": {
      "american": "+125",
      "trueOdds": 2.25
    },
    "matchup": "Athletics @ MIA Marlins",
    "gameTime": "2025-05-04T17:40:00.0000000Z",
    "under": {
      "american": "-175",
      "trueOdds": 1.57142858
    }
  },
  {
    "name": "Agustin Ramirez",
    "line": 1.5,
    "over": {
      "american": "-125",
      "trueOdds": 1.8
    },
    "matchup": "Athletics @ MIA Marlins",
    "gameTime": "2025-05-04T17:40:00.0000000Z",
    "under": {
      "american": "-115",
      "trueOdds": 1.86956522
    }
  },
  {
    "name": "Connor Norby",
    "line": 1.5,
    "over": {
      "american": "-120",
      "trueOdds": 1.83333334
    },
    "matchup": "Athletics @ MIA Marlins",
    "gameTime": "2025-05-04T17:40:00.0000000Z",
    "under": {
      "american": "-120",
      "trueOdds": 1.83333334
    }
  },
  {
    "name": "Dane Myers",
    "line": 1.5,
    "over": {
      "american": "+105",
      "trueOdds": 2.05
    },
    "matchup": "Athletics @ MIA Marlins",
    "gameTime": "2025-05-04T17:40:00.0000000Z",
    "under": {
      "american": "-150",
      "trueOdds": 1.66666667
    }
  },
  {
    "name": "Javier Sanoja",
    "line": 1.5,
    "over": {
      "american": "+120",
      "trueOdds": 2.2
    },
    "matchup": "Athletics @ MIA Marlins",
    "gameTime": "2025-05-04T17:40:00.0000000Z",
    "under": {
      "american": "-170",
      "trueOdds": 1.5882353
    }
  },
  {
    "name": "Xavier Edwards",
    "line": 1.5,
    "over": {
      "american": "-145",
      "trueOdds": 1.68965518
    },
    "matchup": "Athletics @ MIA Marlins",
    "gameTime": "2025-05-04T17:40:00.0000000Z",
    "under": {
      "american": "+100",
      "trueOdds": 2
    }
  },
  {
    "name": "Ronny Simon",
    "line": 1.5,
    "over": {
      "american": "+130",
      "trueOdds": 2.3
    },
    "matchup": "Athletics @ MIA Marlins",
    "gameTime": "2025-05-04T17:40:00.0000000Z",
    "under": {
      "american": "-185",
      "trueOdds": 1.54054055
    }
  },
  {
    "name": "Eric Wagaman",
    "line": 1.5,
    "over": {
      "american": "-125",
      "trueOdds": 1.8
    },
    "matchup": "Athletics @ MIA Marlins",
    "gameTime": "2025-05-04T17:40:00.0000000Z",
    "under": {
      "american": "-115",
      "trueOdds": 1.86956522
    }
  },
  {
    "name": "Corbin Carroll",
    "line": 1.5,
    "over": {
      "american": "-125",
      "trueOdds": 1.8
    },
    "matchup": "ARI Diamondbacks @ PHI Phillies",
    "gameTime": "2025-05-04T18:05:00.0000000Z",
    "under": {
      "american": "-115",
      "trueOdds": 1.86956522
    }
  },
  {
    "name": "Garrett Hampson",
    "line": 1.5,
    "over": {
      "american": "+125",
      "trueOdds": 2.25
    },
    "matchup": "ARI Diamondbacks @ PHI Phillies",
    "gameTime": "2025-05-04T18:05:00.0000000Z",
    "under": {
      "american": "-180",
      "trueOdds": 1.55555556
    }
  },
  {
    "name": "Tim Tawa",
    "line": 1.5,
    "over": {
      "american": "-105",
      "trueOdds": 1.95238096
    },
    "matchup": "ARI Diamondbacks @ PHI Phillies",
    "gameTime": "2025-05-04T18:05:00.0000000Z",
    "under": {
      "american": "-135",
      "trueOdds": 1.74074075
    }
  },
  {
    "name": "Weston Wilson",
    "line": 1.5,
    "over": {
      "american": "+110",
      "trueOdds": 2.1
    },
    "matchup": "ARI Diamondbacks @ PHI Phillies",
    "gameTime": "2025-05-04T18:05:00.0000000Z",
    "under": {
      "american": "-155",
      "trueOdds": 1.6451613
    }
  },
  {
    "name": "Eugenio Suarez",
    "line": 1.5,
    "over": {
      "american": "-125",
      "trueOdds": 1.8
    },
    "matchup": "ARI Diamondbacks @ PHI Phillies",
    "gameTime": "2025-05-04T18:05:00.0000000Z",
    "under": {
      "american": "-115",
      "trueOdds": 1.86956522
    }
  },
  {
    "name": "J.T. Realmuto",
    "line": 1.5,
    "over": {
      "american": "-135",
      "trueOdds": 1.74074075
    },
    "matchup": "ARI Diamondbacks @ PHI Phillies",
    "gameTime": "2025-05-04T18:05:00.0000000Z",
    "under": {
      "american": "-105",
      "trueOdds": 1.95238096
    }
  },
  {
    "name": "Randal Grichuk",
    "line": 1.5,
    "over": {
      "american": "-125",
      "trueOdds": 1.8
    },
    "matchup": "ARI Diamondbacks @ PHI Phillies",
    "gameTime": "2025-05-04T18:05:00.0000000Z",
    "under": {
      "american": "-115",
      "trueOdds": 1.86956522
    }
  },
  {
    "name": "Alec Bohm",
    "line": 1.5,
    "over": {
      "american": "-135",
      "trueOdds": 1.74074075
    },
    "matchup": "ARI Diamondbacks @ PHI Phillies",
    "gameTime": "2025-05-04T18:05:00.0000000Z",
    "under": {
      "american": "-105",
      "trueOdds": 1.95238096
    }
  },
  {
    "name": "Bryce Harper",
    "line": 1.5,
    "over": {
      "american": "-155",
      "trueOdds": 1.6451613
    },
    "matchup": "ARI Diamondbacks @ PHI Phillies",
    "gameTime": "2025-05-04T18:05:00.0000000Z",
    "under": {
      "american": "+110",
      "trueOdds": 2.1
    }
  },
  {
    "name": "Josh Naylor",
    "line": 1.5,
    "over": {
      "american": "-115",
      "trueOdds": 1.86956522
    },
    "matchup": "ARI Diamondbacks @ PHI Phillies",
    "gameTime": "2025-05-04T18:05:00.0000000Z",
    "under": {
      "american": "-120",
      "trueOdds": 1.83333334
    }
  },
  {
    "name": "Nick Castellanos",
    "line": 1.5,
    "over": {
      "american": "-155",
      "trueOdds": 1.6451613
    },
    "matchup": "ARI Diamondbacks @ PHI Phillies",
    "gameTime": "2025-05-04T18:05:00.0000000Z",
    "under": {
      "american": "+110",
      "trueOdds": 2.1
    }
  },
  {
    "name": "Trea Turner",
    "line": 1.5,
    "over": {
      "american": "-165",
      "trueOdds": 1.60606061
    },
    "matchup": "ARI Diamondbacks @ PHI Phillies",
    "gameTime": "2025-05-04T18:05:00.0000000Z",
    "under": {
      "american": "+115",
      "trueOdds": 2.15
    }
  },
  {
    "name": "Edmundo Sosa",
    "line": 1.5,
    "over": {
      "american": "+100",
      "trueOdds": 2
    },
    "matchup": "ARI Diamondbacks @ PHI Phillies",
    "gameTime": "2025-05-04T18:05:00.0000000Z",
    "under": {
      "american": "-140",
      "trueOdds": 1.71428572
    }
  },
  {
    "name": "Lourdes Gurriel Jr.",
    "line": 1.5,
    "over": {
      "american": "-140",
      "trueOdds": 1.71428572
    },
    "matchup": "ARI Diamondbacks @ PHI Phillies",
    "gameTime": "2025-05-04T18:05:00.0000000Z",
    "under": {
      "american": "+100",
      "trueOdds": 2
    }
  },
  {
    "name": "Kyle Schwarber",
    "line": 1.5,
    "over": {
      "american": "-120",
      "trueOdds": 1.83333334
    },
    "matchup": "ARI Diamondbacks @ PHI Phillies",
    "gameTime": "2025-05-04T18:05:00.0000000Z",
    "under": {
      "american": "-120",
      "trueOdds": 1.83333334
    }
  },
  {
    "name": "Johan Rojas",
    "line": 1.5,
    "over": {
      "american": "+115",
      "trueOdds": 2.15
    },
    "matchup": "ARI Diamondbacks @ PHI Phillies",
    "gameTime": "2025-05-04T18:05:00.0000000Z",
    "under": {
      "american": "-160",
      "trueOdds": 1.625
    }
  },
  {
    "name": "Geraldo Perdomo",
    "line": 1.5,
    "over": {
      "american": "-145",
      "trueOdds": 1.68965518
    },
    "matchup": "ARI Diamondbacks @ PHI Phillies",
    "gameTime": "2025-05-04T18:05:00.0000000Z",
    "under": {
      "american": "+100",
      "trueOdds": 2
    }
  },
  {
    "name": "Brendan Rodgers",
    "line": 1.5,
    "over": {
      "american": "+105",
      "trueOdds": 2.05
    },
    "matchup": "HOU Astros @ CHI White Sox",
    "gameTime": "2025-05-04T18:10:00.0000000Z",
    "under": {
      "american": "-150",
      "trueOdds": 1.66666667
    }
  },
  {
    "name": "Jose Altuve",
    "line": 1.5,
    "over": {
      "american": "-150",
      "trueOdds": 1.66666667
    },
    "matchup": "HOU Astros @ CHI White Sox",
    "gameTime": "2025-05-04T18:10:00.0000000Z",
    "under": {
      "american": "+105",
      "trueOdds": 2.05
    }
  },
  {
    "name": "Yainer Diaz",
    "line": 1.5,
    "over": {
      "american": "-160",
      "trueOdds": 1.625
    },
    "matchup": "HOU Astros @ CHI White Sox",
    "gameTime": "2025-05-04T18:10:00.0000000Z",
    "under": {
      "american": "+115",
      "trueOdds": 2.15
    }
  },
  {
    "name": "Victor Caratini",
    "line": 1.5,
    "over": {
      "american": "-110",
      "trueOdds": 1.90909091
    },
    "matchup": "HOU Astros @ CHI White Sox",
    "gameTime": "2025-05-04T18:10:00.0000000Z",
    "under": {
      "american": "-130",
      "trueOdds": 1.76923077
    }
  },
  {
    "name": "Jake Meyers",
    "line": 1.5,
    "over": {
      "american": "-115",
      "trueOdds": 1.86956522
    },
    "matchup": "HOU Astros @ CHI White Sox",
    "gameTime": "2025-05-04T18:10:00.0000000Z",
    "under": {
      "american": "-125",
      "trueOdds": 1.8
    }
  },
  {
    "name": "Christian Walker",
    "line": 1.5,
    "over": {
      "american": "-150",
      "trueOdds": 1.66666667
    },
    "matchup": "HOU Astros @ CHI White Sox",
    "gameTime": "2025-05-04T18:10:00.0000000Z",
    "under": {
      "american": "+105",
      "trueOdds": 2.05
    }
  },
  {
    "name": "Luis Robert",
    "line": 1.5,
    "over": {
      "american": "+110",
      "trueOdds": 2.1
    },
    "matchup": "HOU Astros @ CHI White Sox",
    "gameTime": "2025-05-04T18:10:00.0000000Z",
    "under": {
      "american": "-155",
      "trueOdds": 1.6451613
    }
  },
  {
    "name": "Andrew Vaughn",
    "line": 1.5,
    "over": {
      "american": "+105",
      "trueOdds": 2.05
    },
    "matchup": "HOU Astros @ CHI White Sox",
    "gameTime": "2025-05-04T18:10:00.0000000Z",
    "under": {
      "american": "-145",
      "trueOdds": 1.68965518
    }
  },
  {
    "name": "Andrew Benintendi",
    "line": 1.5,
    "over": {
      "american": "+105",
      "trueOdds": 2.05
    },
    "matchup": "HOU Astros @ CHI White Sox",
    "gameTime": "2025-05-04T18:10:00.0000000Z",
    "under": {
      "american": "-150",
      "trueOdds": 1.66666667
    }
  },
  {
    "name": "Edgar Quero",
    "line": 1.5,
    "over": {
      "american": "+110",
      "trueOdds": 2.1
    },
    "matchup": "HOU Astros @ CHI White Sox",
    "gameTime": "2025-05-04T18:10:00.0000000Z",
    "under": {
      "american": "-155",
      "trueOdds": 1.6451613
    }
  },
  {
    "name": "Miguel Vargas",
    "line": 1.5,
    "over": {
      "american": "+115",
      "trueOdds": 2.15
    },
    "matchup": "HOU Astros @ CHI White Sox",
    "gameTime": "2025-05-04T18:10:00.0000000Z",
    "under": {
      "american": "-165",
      "trueOdds": 1.60606061
    }
  },
  {
    "name": "Chase Meidroth",
    "line": 1.5,
    "over": {
      "american": "+120",
      "trueOdds": 2.2
    },
    "matchup": "HOU Astros @ CHI White Sox",
    "gameTime": "2025-05-04T18:10:00.0000000Z",
    "under": {
      "american": "-170",
      "trueOdds": 1.5882353
    }
  },
  {
    "name": "Lenyn Sosa",
    "line": 1.5,
    "over": {
      "american": "+120",
      "trueOdds": 2.2
    },
    "matchup": "HOU Astros @ CHI White Sox",
    "gameTime": "2025-05-04T18:10:00.0000000Z",
    "under": {
      "american": "-175",
      "trueOdds": 1.57142858
    }
  },
  {
    "name": "Mauricio Dubon",
    "line": 1.5,
    "over": {
      "american": "+100",
      "trueOdds": 2
    },
    "matchup": "HOU Astros @ CHI White Sox",
    "gameTime": "2025-05-04T18:10:00.0000000Z",
    "under": {
      "american": "-145",
      "trueOdds": 1.68965518
    }
  },
  {
    "name": "Zach Dezenzo",
    "line": 1.5,
    "over": {
      "american": "-110",
      "trueOdds": 1.90909091
    },
    "matchup": "HOU Astros @ CHI White Sox",
    "gameTime": "2025-05-04T18:10:00.0000000Z",
    "under": {
      "american": "-125",
      "trueOdds": 1.8
    }
  },
  {
    "name": "Rhys Hoskins",
    "line": 1.5,
    "over": {
      "american": "-105",
      "trueOdds": 1.95238096
    },
    "matchup": "CHI Cubs @ MIL Brewers",
    "gameTime": "2025-05-04T18:10:00.0000000Z",
    "under": {
      "american": "-135",
      "trueOdds": 1.74074075
    }
  },
  {
    "name": "Brice Turang",
    "line": 1.5,
    "over": {
      "american": "+130",
      "trueOdds": 2.3
    },
    "matchup": "CHI Cubs @ MIL Brewers",
    "gameTime": "2025-05-04T18:10:00.0000000Z",
    "under": {
      "american": "-185",
      "trueOdds": 1.54054055
    }
  },
  {
    "name": "Isaac Collins",
    "line": 1.5,
    "over": {
      "american": "+105",
      "trueOdds": 2.05
    },
    "matchup": "CHI Cubs @ MIL Brewers",
    "gameTime": "2025-05-04T18:10:00.0000000Z",
    "under": {
      "american": "-150",
      "trueOdds": 1.66666667
    }
  },
  {
    "name": "Jon Berti",
    "line": 1.5,
    "over": {
      "american": "+120",
      "trueOdds": 2.2
    },
    "matchup": "CHI Cubs @ MIL Brewers",
    "gameTime": "2025-05-04T18:10:00.0000000Z",
    "under": {
      "american": "-170",
      "trueOdds": 1.5882353
    }
  },
  {
    "name": "Pete Crow-Armstrong",
    "line": 1.5,
    "over": {
      "american": "-105",
      "trueOdds": 1.95238096
    },
    "matchup": "CHI Cubs @ MIL Brewers",
    "gameTime": "2025-05-04T18:10:00.0000000Z",
    "under": {
      "american": "-135",
      "trueOdds": 1.74074075
    }
  },
  {
    "name": "Ian Happ",
    "line": 1.5,
    "over": {
      "american": "-105",
      "trueOdds": 1.95238096
    },
    "matchup": "CHI Cubs @ MIL Brewers",
    "gameTime": "2025-05-04T18:10:00.0000000Z",
    "under": {
      "american": "-135",
      "trueOdds": 1.74074075
    }
  },
  {
    "name": "Kyle Tucker",
    "line": 1.5,
    "over": {
      "american": "-120",
      "trueOdds": 1.83333334
    },
    "matchup": "CHI Cubs @ MIL Brewers",
    "gameTime": "2025-05-04T18:10:00.0000000Z",
    "under": {
      "american": "-120",
      "trueOdds": 1.83333334
    }
  },
  {
    "name": "Nico Hoerner",
    "line": 1.5,
    "over": {
      "american": "-115",
      "trueOdds": 1.86956522
    },
    "matchup": "CHI Cubs @ MIL Brewers",
    "gameTime": "2025-05-04T18:10:00.0000000Z",
    "under": {
      "american": "-125",
      "trueOdds": 1.8
    }
  },
  {
    "name": "Caleb Durbin",
    "line": 1.5,
    "over": {
      "american": "+130",
      "trueOdds": 2.3
    },
    "matchup": "CHI Cubs @ MIL Brewers",
    "gameTime": "2025-05-04T18:10:00.0000000Z",
    "under": {
      "american": "-185",
      "trueOdds": 1.54054055
    }
  },
  {
    "name": "Christian Yelich",
    "line": 1.5,
    "over": {
      "american": "-110",
      "trueOdds": 1.90909091
    },
    "matchup": "CHI Cubs @ MIL Brewers",
    "gameTime": "2025-05-04T18:10:00.0000000Z",
    "under": {
      "american": "-130",
      "trueOdds": 1.76923077
    }
  },
  {
    "name": "Miguel Amaya",
    "line": 1.5,
    "over": {
      "american": "+120",
      "trueOdds": 2.2
    },
    "matchup": "CHI Cubs @ MIL Brewers",
    "gameTime": "2025-05-04T18:10:00.0000000Z",
    "under": {
      "american": "-165",
      "trueOdds": 1.60606061
    }
  },
  {
    "name": "Jackson Chourio",
    "line": 1.5,
    "over": {
      "american": "-140",
      "trueOdds": 1.71428572
    },
    "matchup": "CHI Cubs @ MIL Brewers",
    "gameTime": "2025-05-04T18:10:00.0000000Z",
    "under": {
      "american": "+100",
      "trueOdds": 2
    }
  },
  {
    "name": "Michael Busch",
    "line": 1.5,
    "over": {
      "american": "+115",
      "trueOdds": 2.15
    },
    "matchup": "CHI Cubs @ MIL Brewers",
    "gameTime": "2025-05-04T18:10:00.0000000Z",
    "under": {
      "american": "-165",
      "trueOdds": 1.60606061
    }
  },
  {
    "name": "Seiya Suzuki",
    "line": 1.5,
    "over": {
      "american": "+100",
      "trueOdds": 2
    },
    "matchup": "CHI Cubs @ MIL Brewers",
    "gameTime": "2025-05-04T18:10:00.0000000Z",
    "under": {
      "american": "-140",
      "trueOdds": 1.71428572
    }
  },
  {
    "name": "William Contreras",
    "line": 1.5,
    "over": {
      "american": "-125",
      "trueOdds": 1.8
    },
    "matchup": "CHI Cubs @ MIL Brewers",
    "gameTime": "2025-05-04T18:10:00.0000000Z",
    "under": {
      "american": "-115",
      "trueOdds": 1.86956522
    }
  },
  {
    "name": "Sal Frelick",
    "line": 1.5,
    "over": {
      "american": "+125",
      "trueOdds": 2.25
    },
    "matchup": "CHI Cubs @ MIL Brewers",
    "gameTime": "2025-05-04T18:10:00.0000000Z",
    "under": {
      "american": "-175",
      "trueOdds": 1.57142858
    }
  },
  {
    "name": "Joey Ortiz",
    "line": 1.5,
    "over": {
      "american": "+130",
      "trueOdds": 2.3
    },
    "matchup": "CHI Cubs @ MIL Brewers",
    "gameTime": "2025-05-04T18:10:00.0000000Z",
    "under": {
      "american": "-180",
      "trueOdds": 1.55555556
    }
  },
  {
    "name": "Ben Williamson",
    "line": 1.5,
    "over": {
      "american": "+120",
      "trueOdds": 2.2
    },
    "matchup": "SEA Mariners @ TEX Rangers",
    "gameTime": "2025-05-04T18:35:00.0000000Z",
    "under": {
      "american": "-170",
      "trueOdds": 1.5882353
    }
  },
  {
    "name": "Blaine Crim",
    "line": 1.5,
    "over": {
      "american": "+110",
      "trueOdds": 2.1
    },
    "matchup": "SEA Mariners @ TEX Rangers",
    "gameTime": "2025-05-04T18:35:00.0000000Z",
    "under": {
      "american": "-150",
      "trueOdds": 1.66666667
    }
  },
  {
    "name": "Marcus Semien",
    "line": 1.5,
    "over": {
      "american": "-135",
      "trueOdds": 1.74074075
    },
    "matchup": "SEA Mariners @ TEX Rangers",
    "gameTime": "2025-05-04T18:35:00.0000000Z",
    "under": {
      "american": "-105",
      "trueOdds": 1.95238096
    }
  },
  {
    "name": "Joc Pederson",
    "line": 1.5,
    "over": {
      "american": "-120",
      "trueOdds": 1.83333334
    },
    "matchup": "SEA Mariners @ TEX Rangers",
    "gameTime": "2025-05-04T18:35:00.0000000Z",
    "under": {
      "american": "-120",
      "trueOdds": 1.83333334
    }
  },
  {
    "name": "Jorge Polanco",
    "line": 1.5,
    "over": {
      "american": "+100",
      "trueOdds": 2
    },
    "matchup": "SEA Mariners @ TEX Rangers",
    "gameTime": "2025-05-04T18:35:00.0000000Z",
    "under": {
      "american": "-140",
      "trueOdds": 1.71428572
    }
  },
  {
    "name": "Cal Raleigh",
    "line": 1.5,
    "over": {
      "american": "-105",
      "trueOdds": 1.95238096
    },
    "matchup": "SEA Mariners @ TEX Rangers",
    "gameTime": "2025-05-04T18:35:00.0000000Z",
    "under": {
      "american": "-135",
      "trueOdds": 1.74074075
    }
  },
  {
    "name": "Julio Rodriguez",
    "line": 1.5,
    "over": {
      "american": "-125",
      "trueOdds": 1.8
    },
    "matchup": "SEA Mariners @ TEX Rangers",
    "gameTime": "2025-05-04T18:35:00.0000000Z",
    "under": {
      "american": "-115",
      "trueOdds": 1.86956522
    }
  },
  {
    "name": "Randy Arozarena",
    "line": 1.5,
    "over": {
      "american": "+115",
      "trueOdds": 2.15
    },
    "matchup": "SEA Mariners @ TEX Rangers",
    "gameTime": "2025-05-04T18:35:00.0000000Z",
    "under": {
      "american": "-160",
      "trueOdds": 1.625
    }
  },
  {
    "name": "Adolis Garcia",
    "line": 1.5,
    "over": {
      "american": "-125",
      "trueOdds": 1.8
    },
    "matchup": "SEA Mariners @ TEX Rangers",
    "gameTime": "2025-05-04T18:35:00.0000000Z",
    "under": {
      "american": "-110",
      "trueOdds": 1.90909091
    }
  },
  {
    "name": "J.P. Crawford",
    "line": 1.5,
    "over": {
      "american": "+110",
      "trueOdds": 2.1
    },
    "matchup": "SEA Mariners @ TEX Rangers",
    "gameTime": "2025-05-04T18:35:00.0000000Z",
    "under": {
      "american": "-155",
      "trueOdds": 1.6451613
    }
  },
  {
    "name": "Josh Smith",
    "line": 1.5,
    "over": {
      "american": "-145",
      "trueOdds": 1.68965518
    },
    "matchup": "SEA Mariners @ TEX Rangers",
    "gameTime": "2025-05-04T18:35:00.0000000Z",
    "under": {
      "american": "+105",
      "trueOdds": 2.05
    }
  },
  {
    "name": "Josh Jung",
    "line": 1.5,
    "over": {
      "american": "-115",
      "trueOdds": 1.86956522
    },
    "matchup": "SEA Mariners @ TEX Rangers",
    "gameTime": "2025-05-04T18:35:00.0000000Z",
    "under": {
      "american": "-120",
      "trueOdds": 1.83333334
    }
  },
  {
    "name": "Jonah Heim",
    "line": 1.5,
    "over": {
      "american": "-105",
      "trueOdds": 1.95238096
    },
    "matchup": "SEA Mariners @ TEX Rangers",
    "gameTime": "2025-05-04T18:35:00.0000000Z",
    "under": {
      "american": "-135",
      "trueOdds": 1.74074075
    }
  },
  {
    "name": "Wilmer Flores (SF)",
    "line": 1.5,
    "over": {
      "american": "-135",
      "trueOdds": 1.74074075
    },
    "matchup": "COL Rockies @ SF Giants",
    "gameTime": "2025-05-04T20:05:00.0000000Z",
    "under": {
      "american": "-105",
      "trueOdds": 1.95238096
    }
  },
  {
    "name": "Christian Koss",
    "line": 1.5,
    "over": {
      "american": "-115",
      "trueOdds": 1.86956522
    },
    "matchup": "COL Rockies @ SF Giants",
    "gameTime": "2025-05-04T20:05:00.0000000Z",
    "under": {
      "american": "-125",
      "trueOdds": 1.8
    }
  },
  {
    "name": "Ryan McMahon",
    "line": 1.5,
    "over": {
      "american": "+130",
      "trueOdds": 2.3
    },
    "matchup": "COL Rockies @ SF Giants",
    "gameTime": "2025-05-04T20:05:00.0000000Z",
    "under": {
      "american": "-180",
      "trueOdds": 1.55555556
    }
  },
  {
    "name": "Patrick Bailey",
    "line": 1.5,
    "over": {
      "american": "-115",
      "trueOdds": 1.86956522
    },
    "matchup": "COL Rockies @ SF Giants",
    "gameTime": "2025-05-04T20:05:00.0000000Z",
    "under": {
      "american": "-120",
      "trueOdds": 1.83333334
    }
  },
  {
    "name": "Hunter Goodman",
    "line": 1.5,
    "over": {
      "american": "+105",
      "trueOdds": 2.05
    },
    "matchup": "COL Rockies @ SF Giants",
    "gameTime": "2025-05-04T20:05:00.0000000Z",
    "under": {
      "american": "-150",
      "trueOdds": 1.66666667
    }
  },
  {
    "name": "Jordan Beck",
    "line": 1.5,
    "over": {
      "american": "+120",
      "trueOdds": 2.2
    },
    "matchup": "COL Rockies @ SF Giants",
    "gameTime": "2025-05-04T20:05:00.0000000Z",
    "under": {
      "american": "-165",
      "trueOdds": 1.60606061
    }
  },
  {
    "name": "Heliot Ramos",
    "line": 1.5,
    "over": {
      "american": "-160",
      "trueOdds": 1.625
    },
    "matchup": "COL Rockies @ SF Giants",
    "gameTime": "2025-05-04T20:05:00.0000000Z",
    "under": {
      "american": "+115",
      "trueOdds": 2.15
    }
  },
  {
    "name": "LaMonte Wade Jr.",
    "line": 1.5,
    "over": {
      "american": "-110",
      "trueOdds": 1.90909091
    },
    "matchup": "COL Rockies @ SF Giants",
    "gameTime": "2025-05-04T20:05:00.0000000Z",
    "under": {
      "american": "-130",
      "trueOdds": 1.76923077
    }
  },
  {
    "name": "Brenton Doyle",
    "line": 1.5,
    "over": {
      "american": "-110",
      "trueOdds": 1.90909091
    },
    "matchup": "COL Rockies @ SF Giants",
    "gameTime": "2025-05-04T20:05:00.0000000Z",
    "under": {
      "american": "-130",
      "trueOdds": 1.76923077
    }
  },
  {
    "name": "Travis d'Arnaud",
    "line": 1.5,
    "over": {
      "american": "+125",
      "trueOdds": 2.25
    },
    "matchup": "DET Tigers @ LA Angels",
    "gameTime": "2025-05-04T20:07:00.0000000Z",
    "under": {
      "american": "-175",
      "trueOdds": 1.57142858
    }
  },
  {
    "name": "Javier Baez",
    "line": 1.5,
    "over": {
      "american": "+105",
      "trueOdds": 2.05
    },
    "matchup": "DET Tigers @ LA Angels",
    "gameTime": "2025-05-04T20:07:00.0000000Z",
    "under": {
      "american": "-145",
      "trueOdds": 1.68965518
    }
  },
  {
    "name": "Gleyber Torres",
    "line": 1.5,
    "over": {
      "american": "-145",
      "trueOdds": 1.68965518
    },
    "matchup": "DET Tigers @ LA Angels",
    "gameTime": "2025-05-04T20:07:00.0000000Z",
    "under": {
      "american": "+105",
      "trueOdds": 2.05
    }
  },
  {
    "name": "Zach McKinstry",
    "line": 1.5,
    "over": {
      "american": "-145",
      "trueOdds": 1.68965518
    },
    "matchup": "DET Tigers @ LA Angels",
    "gameTime": "2025-05-04T20:07:00.0000000Z",
    "under": {
      "american": "+100",
      "trueOdds": 2
    }
  },
  {
    "name": "Spencer Torkelson",
    "line": 1.5,
    "over": {
      "american": "-115",
      "trueOdds": 1.86956522
    },
    "matchup": "DET Tigers @ LA Angels",
    "gameTime": "2025-05-04T20:07:00.0000000Z",
    "under": {
      "american": "-125",
      "trueOdds": 1.8
    }
  },
  {
    "name": "Dillon Dingler",
    "line": 1.5,
    "over": {
      "american": "+100",
      "trueOdds": 2
    },
    "matchup": "DET Tigers @ LA Angels",
    "gameTime": "2025-05-04T20:07:00.0000000Z",
    "under": {
      "american": "-140",
      "trueOdds": 1.71428572
    }
  },
  {
    "name": "Logan O'Hoppe",
    "line": 1.5,
    "over": {
      "american": "+110",
      "trueOdds": 2.1
    },
    "matchup": "DET Tigers @ LA Angels",
    "gameTime": "2025-05-04T20:07:00.0000000Z",
    "under": {
      "american": "-150",
      "trueOdds": 1.66666667
    }
  },
  {
    "name": "Jorge Soler",
    "line": 1.5,
    "over": {
      "american": "+105",
      "trueOdds": 2.05
    },
    "matchup": "DET Tigers @ LA Angels",
    "gameTime": "2025-05-04T20:07:00.0000000Z",
    "under": {
      "american": "-150",
      "trueOdds": 1.66666667
    }
  },
  {
    "name": "Nolan Schanuel",
    "line": 1.5,
    "over": {
      "american": "+100",
      "trueOdds": 2
    },
    "matchup": "DET Tigers @ LA Angels",
    "gameTime": "2025-05-04T20:07:00.0000000Z",
    "under": {
      "american": "-140",
      "trueOdds": 1.71428572
    }
  },
  {
    "name": "Taylor Ward",
    "line": 1.5,
    "over": {
      "american": "+100",
      "trueOdds": 2
    },
    "matchup": "DET Tigers @ LA Angels",
    "gameTime": "2025-05-04T20:07:00.0000000Z",
    "under": {
      "american": "-145",
      "trueOdds": 1.68965518
    }
  },
  {
    "name": "Trey Sweeney",
    "line": 1.5,
    "over": {
      "american": "-110",
      "trueOdds": 1.90909091
    },
    "matchup": "DET Tigers @ LA Angels",
    "gameTime": "2025-05-04T20:07:00.0000000Z",
    "under": {
      "american": "-125",
      "trueOdds": 1.8
    }
  },
  {
    "name": "Luis Rengifo",
    "line": 1.5,
    "over": {
      "american": "+115",
      "trueOdds": 2.15
    },
    "matchup": "DET Tigers @ LA Angels",
    "gameTime": "2025-05-04T20:07:00.0000000Z",
    "under": {
      "american": "-165",
      "trueOdds": 1.60606061
    }
  },
  {
    "name": "Jace Jung",
    "line": 1.5,
    "over": {
      "american": "+100",
      "trueOdds": 2
    },
    "matchup": "DET Tigers @ LA Angels",
    "gameTime": "2025-05-04T20:07:00.0000000Z",
    "under": {
      "american": "-140",
      "trueOdds": 1.71428572
    }
  },
  {
    "name": "Zach Neto",
    "line": 1.5,
    "over": {
      "american": "+100",
      "trueOdds": 2
    },
    "matchup": "DET Tigers @ LA Angels",
    "gameTime": "2025-05-04T20:07:00.0000000Z",
    "under": {
      "american": "-145",
      "trueOdds": 1.68965518
    }
  },
  {
    "name": "Tyler Stephenson",
    "line": 1.5,
    "over": {
      "american": "-105",
      "trueOdds": 1.95238096
    },
    "matchup": "WAS Nationals @ CIN Reds",
    "gameTime": "2025-05-04T20:10:00.0000000Z",
    "under": {
      "american": "-135",
      "trueOdds": 1.74074075
    }
  },
  {
    "name": "Elly De La Cruz",
    "line": 1.5,
    "over": {
      "american": "+105",
      "trueOdds": 2.05
    },
    "matchup": "WAS Nationals @ CIN Reds",
    "gameTime": "2025-05-04T20:10:00.0000000Z",
    "under": {
      "american": "-150",
      "trueOdds": 1.66666667
    }
  },
  {
    "name": "Noelvi Marte",
    "line": 1.5,
    "over": {
      "american": "-105",
      "trueOdds": 1.95238096
    },
    "matchup": "WAS Nationals @ CIN Reds",
    "gameTime": "2025-05-04T20:10:00.0000000Z",
    "under": {
      "american": "-135",
      "trueOdds": 1.74074075
    }
  },
  {
    "name": "Matt McLain",
    "line": 1.5,
    "over": {
      "american": "+100",
      "trueOdds": 2
    },
    "matchup": "WAS Nationals @ CIN Reds",
    "gameTime": "2025-05-04T20:10:00.0000000Z",
    "under": {
      "american": "-140",
      "trueOdds": 1.71428572
    }
  },
  {
    "name": "CJ Abrams",
    "line": 1.5,
    "over": {
      "american": "-135",
      "trueOdds": 1.74074075
    },
    "matchup": "WAS Nationals @ CIN Reds",
    "gameTime": "2025-05-04T20:10:00.0000000Z",
    "under": {
      "american": "-105",
      "trueOdds": 1.95238096
    }
  },
  {
    "name": "Luis Garcia (WAS)",
    "line": 1.5,
    "over": {
      "american": "-115",
      "trueOdds": 1.86956522
    },
    "matchup": "WAS Nationals @ CIN Reds",
    "gameTime": "2025-05-04T20:10:00.0000000Z",
    "under": {
      "american": "-120",
      "trueOdds": 1.83333334
    }
  },
  {
    "name": "TJ Friedl",
    "line": 1.5,
    "over": {
      "american": "+115",
      "trueOdds": 2.15
    },
    "matchup": "WAS Nationals @ CIN Reds",
    "gameTime": "2025-05-04T20:10:00.0000000Z",
    "under": {
      "american": "-165",
      "trueOdds": 1.60606061
    }
  },
  {
    "name": "Dylan Crews",
    "line": 1.5,
    "over": {
      "american": "-115",
      "trueOdds": 1.86956522
    },
    "matchup": "WAS Nationals @ CIN Reds",
    "gameTime": "2025-05-04T20:10:00.0000000Z",
    "under": {
      "american": "-120",
      "trueOdds": 1.83333334
    }
  },
  {
    "name": "Keibert Ruiz",
    "line": 1.5,
    "over": {
      "american": "-110",
      "trueOdds": 1.90909091
    },
    "matchup": "WAS Nationals @ CIN Reds",
    "gameTime": "2025-05-04T20:10:00.0000000Z",
    "under": {
      "american": "-130",
      "trueOdds": 1.76923077
    }
  },
  {
    "name": "Jose Trevino",
    "line": 1.5,
    "over": {
      "american": "+130",
      "trueOdds": 2.3
    },
    "matchup": "WAS Nationals @ CIN Reds",
    "gameTime": "2025-05-04T20:10:00.0000000Z",
    "under": {
      "american": "-185",
      "trueOdds": 1.54054055
    }
  },
  {
    "name": "Spencer Steer",
    "line": 1.5,
    "over": {
      "american": "+105",
      "trueOdds": 2.05
    },
    "matchup": "WAS Nationals @ CIN Reds",
    "gameTime": "2025-05-04T20:10:00.0000000Z",
    "under": {
      "american": "-145",
      "trueOdds": 1.68965518
    }
  },
  {
    "name": "Jose Tena",
    "line": 1.5,
    "over": {
      "american": "-105",
      "trueOdds": 1.95238096
    },
    "matchup": "WAS Nationals @ CIN Reds",
    "gameTime": "2025-05-04T20:10:00.0000000Z",
    "under": {
      "american": "-135",
      "trueOdds": 1.74074075
    }
  },
  {
    "name": "Nathaniel Lowe",
    "line": 1.5,
    "over": {
      "american": "-105",
      "trueOdds": 1.95238096
    },
    "matchup": "WAS Nationals @ CIN Reds",
    "gameTime": "2025-05-04T20:10:00.0000000Z",
    "under": {
      "american": "-135",
      "trueOdds": 1.74074075
    }
  },
  {
    "name": "Jacob Young",
    "line": 1.5,
    "over": {
      "american": "+120",
      "trueOdds": 2.2
    },
    "matchup": "WAS Nationals @ CIN Reds",
    "gameTime": "2025-05-04T20:10:00.0000000Z",
    "under": {
      "american": "-170",
      "trueOdds": 1.5882353
    }
  },
  {
    "name": "Santiago Espinal",
    "line": 1.5,
    "over": {
      "american": "-115",
      "trueOdds": 1.86956522
    },
    "matchup": "WAS Nationals @ CIN Reds",
    "gameTime": "2025-05-04T20:10:00.0000000Z",
    "under": {
      "american": "-120",
      "trueOdds": 1.83333334
    }
  },
  {
    "name": "Alex Call",
    "line": 1.5,
    "over": {
      "american": "+105",
      "trueOdds": 2.05
    },
    "matchup": "WAS Nationals @ CIN Reds",
    "gameTime": "2025-05-04T20:10:00.0000000Z",
    "under": {
      "american": "-150",
      "trueOdds": 1.66666667
    }
  },
  {
    "name": "James Wood",
    "line": 1.5,
    "over": {
      "american": "-105",
      "trueOdds": 1.95238096
    },
    "matchup": "WAS Nationals @ CIN Reds",
    "gameTime": "2025-05-04T20:10:00.0000000Z",
    "under": {
      "american": "-135",
      "trueOdds": 1.74074075
    }
  },
  {
    "name": "Max Muncy (LAD)",
    "line": 1.5,
    "over": {
      "american": "-110",
      "trueOdds": 1.90909091
    },
    "matchup": "LA Dodgers @ ATL Braves",
    "gameTime": "2025-05-04T23:10:00.0000000Z",
    "under": {
      "american": "-130",
      "trueOdds": 1.76923077
    }
  },
  {
    "name": "Michael Conforto",
    "line": 1.5,
    "over": {
      "american": "+105",
      "trueOdds": 2.05
    },
    "matchup": "LA Dodgers @ ATL Braves",
    "gameTime": "2025-05-04T23:10:00.0000000Z",
    "under": {
      "american": "-145",
      "trueOdds": 1.68965518
    }
  },
  {
    "name": "Will Smith (LAD)",
    "line": 1.5,
    "over": {
      "american": "-150",
      "trueOdds": 1.66666667
    },
    "matchup": "LA Dodgers @ ATL Braves",
    "gameTime": "2025-05-04T23:10:00.0000000Z",
    "under": {
      "american": "+105",
      "trueOdds": 2.05
    }
  },
  {
    "name": "Hyeseong Kim",
    "line": 1.5,
    "over": {
      "american": "-110",
      "trueOdds": 1.90909091
    },
    "matchup": "LA Dodgers @ ATL Braves",
    "gameTime": "2025-05-04T23:10:00.0000000Z",
    "under": {
      "american": "-130",
      "trueOdds": 1.76923077
    }
  },
  {
    "name": "Andy Pages",
    "line": 1.5,
    "over": {
      "american": "-130",
      "trueOdds": 1.76923077
    },
    "matchup": "LA Dodgers @ ATL Braves",
    "gameTime": "2025-05-04T23:10:00.0000000Z",
    "under": {
      "american": "-110",
      "trueOdds": 1.90909091
    }
  },
  {
    "name": "Teoscar Hernandez",
    "line": 1.5,
    "over": {
      "american": "-155",
      "trueOdds": 1.6451613
    },
    "matchup": "LA Dodgers @ ATL Braves",
    "gameTime": "2025-05-04T23:10:00.0000000Z",
    "under": {
      "american": "+110",
      "trueOdds": 2.1
    }
  },
  {
    "name": "Marcell Ozuna",
    "line": 1.5,
    "over": {
      "american": "-115",
      "trueOdds": 1.86956522
    },
    "matchup": "LA Dodgers @ ATL Braves",
    "gameTime": "2025-05-04T23:10:00.0000000Z",
    "under": {
      "american": "-120",
      "trueOdds": 1.83333334
    }
  },
  {
    "name": "Austin Riley",
    "line": 1.5,
    "over": {
      "american": "-130",
      "trueOdds": 1.76923077
    },
    "matchup": "LA Dodgers @ ATL Braves",
    "gameTime": "2025-05-04T23:10:00.0000000Z",
    "under": {
      "american": "-110",
      "trueOdds": 1.90909091
    }
  },
  {
    "name": "Matt Olson",
    "line": 1.5,
    "over": {
      "american": "+110",
      "trueOdds": 2.1
    },
    "matchup": "LA Dodgers @ ATL Braves",
    "gameTime": "2025-05-04T23:10:00.0000000Z",
    "under": {
      "american": "-155",
      "trueOdds": 1.6451613
    }
  },
  {
    "name": "Eli White",
    "line": 1.5,
    "over": {
      "american": "+115",
      "trueOdds": 2.15
    },
    "matchup": "LA Dodgers @ ATL Braves",
    "gameTime": "2025-05-04T23:10:00.0000000Z",
    "under": {
      "american": "-160",
      "trueOdds": 1.625
    }
  },
  {
    "name": "Ozzie Albies",
    "line": 1.5,
    "over": {
      "american": "+105",
      "trueOdds": 2.05
    },
    "matchup": "LA Dodgers @ ATL Braves",
    "gameTime": "2025-05-04T23:10:00.0000000Z",
    "under": {
      "american": "-150",
      "trueOdds": 1.66666667
    }
  },
  {
    "name": "Nick Allen",
    "line": 1.5,
    "over": {
      "american": "+135",
      "trueOdds": 2.35
    },
    "matchup": "LA Dodgers @ ATL Braves",
    "gameTime": "2025-05-04T23:10:00.0000000Z",
    "under": {
      "american": "-195",
      "trueOdds": 1.51282052
    }
  },
  {
    "name": "Michael Harris",
    "line": 1.5,
    "over": {
      "american": "+105",
      "trueOdds": 2.05
    },
    "matchup": "LA Dodgers @ ATL Braves",
    "gameTime": "2025-05-04T23:10:00.0000000Z",
    "under": {
      "american": "-150",
      "trueOdds": 1.66666667
    }
  },
  {
    "name": "Sean Murphy",
    "line": 1.5,
    "over": {
      "american": "+120",
      "trueOdds": 2.2
    },
    "matchup": "LA Dodgers @ ATL Braves",
    "gameTime": "2025-05-04T23:10:00.0000000Z",
    "under": {
      "american": "-165",
      "trueOdds": 1.60606061
    }
  },
  {
    "name": "Alex Verdugo",
    "line": 1.5,
    "over": {
      "american": "-105",
      "trueOdds": 1.95238096
    },
    "matchup": "LA Dodgers @ ATL Braves",
    "gameTime": "2025-05-04T23:10:00.0000000Z",
    "under": {
      "american": "-135",
      "trueOdds": 1.74074075
    }
  },
  {
    "name": "Bobby Witt Jr.",
    "line": 2.5,
    "over": {
      "american": "+105",
      "trueOdds": 2.05
    },
    "matchup": "KC Royals @ BAL Orioles",
    "gameTime": "2025-05-04T17:35:00.0000000Z",
    "under": {
      "american": "-145",
      "trueOdds": 1.68965518
    }
  },
  {
    "name": "Alex Bregman",
    "line": 2.5,
    "over": {
      "american": "+120",
      "trueOdds": 2.2
    },
    "matchup": "MIN Twins @ BOS Red Sox",
    "gameTime": "2025-05-04T17:35:00.0000000Z",
    "under": {
      "american": "-170",
      "trueOdds": 1.5882353
    }
  },
  {
    "name": "Jarren Duran",
    "line": 2.5,
    "over": {
      "american": "-105",
      "trueOdds": 1.95238096
    },
    "matchup": "MIN Twins @ BOS Red Sox",
    "gameTime": "2025-05-04T17:35:00.0000000Z",
    "under": {
      "american": "-135",
      "trueOdds": 1.74074075
    }
  },
  {
    "name": "Rafael Devers",
    "line": 2.5,
    "over": {
      "american": "+115",
      "trueOdds": 2.15
    },
    "matchup": "MIN Twins @ BOS Red Sox",
    "gameTime": "2025-05-04T17:35:00.0000000Z",
    "under": {
      "american": "-160",
      "trueOdds": 1.625
    }
  },
  {
    "name": "Aaron Judge",
    "line": 2.5,
    "over": {
      "american": "-115",
      "trueOdds": 1.86956522
    },
    "matchup": "TB Rays @ NY Yankees",
    "gameTime": "2025-05-04T17:35:00.0000000Z",
    "under": {
      "american": "-120",
      "trueOdds": 1.83333334
    }
  },
  {
    "name": "Fernando Tatis Jr.",
    "line": 2.5,
    "over": {
      "american": "+115",
      "trueOdds": 2.15
    },
    "matchup": "SD Padres @ PIT Pirates",
    "gameTime": "2025-05-04T17:35:00.0000000Z",
    "under": {
      "american": "-160",
      "trueOdds": 1.625
    }
  },
  {
    "name": "Jeremy Pena",
    "line": 2.5,
    "over": {
      "american": "+115",
      "trueOdds": 2.15
    },
    "matchup": "HOU Astros @ CHI White Sox",
    "gameTime": "2025-05-04T18:10:00.0000000Z",
    "under": {
      "american": "-160",
      "trueOdds": 1.625
    }
  },
  {
    "name": "Wyatt Langford",
    "line": 2.5,
    "over": {
      "american": "+105",
      "trueOdds": 2.05
    },
    "matchup": "SEA Mariners @ TEX Rangers",
    "gameTime": "2025-05-04T18:35:00.0000000Z",
    "under": {
      "american": "-150",
      "trueOdds": 1.66666667
    }
  },
  {
    "name": "Corey Seager",
    "line": 2.5,
    "over": {
      "american": "+115",
      "trueOdds": 2.15
    },
    "matchup": "SEA Mariners @ TEX Rangers",
    "gameTime": "2025-05-04T18:35:00.0000000Z",
    "under": {
      "american": "-160",
      "trueOdds": 1.625
    }
  },
  {
    "name": "Matt Chapman",
    "line": 2.5,
    "over": {
      "american": "+110",
      "trueOdds": 2.1
    },
    "matchup": "COL Rockies @ SF Giants",
    "gameTime": "2025-05-04T20:05:00.0000000Z",
    "under": {
      "american": "-150",
      "trueOdds": 1.66666667
    }
  },
  {
    "name": "Mike Yastrzemski",
    "line": 2.5,
    "over": {
      "american": "+110",
      "trueOdds": 2.1
    },
    "matchup": "COL Rockies @ SF Giants",
    "gameTime": "2025-05-04T20:05:00.0000000Z",
    "under": {
      "american": "-155",
      "trueOdds": 1.6451613
    }
  },
  {
    "name": "Willy Adames",
    "line": 2.5,
    "over": {
      "american": "+110",
      "trueOdds": 2.1
    },
    "matchup": "COL Rockies @ SF Giants",
    "gameTime": "2025-05-04T20:05:00.0000000Z",
    "under": {
      "american": "-155",
      "trueOdds": 1.6451613
    }
  },
  {
    "name": "Jung Hoo Lee",
    "line": 2.5,
    "over": {
      "american": "+110",
      "trueOdds": 2.1
    },
    "matchup": "COL Rockies @ SF Giants",
    "gameTime": "2025-05-04T20:05:00.0000000Z",
    "under": {
      "american": "-160",
      "trueOdds": 1.625
    }
  },
  {
    "name": "Kerry Carpenter",
    "line": 2.5,
    "over": {
      "american": "+105",
      "trueOdds": 2.05
    },
    "matchup": "DET Tigers @ LA Angels",
    "gameTime": "2025-05-04T20:07:00.0000000Z",
    "under": {
      "american": "-150",
      "trueOdds": 1.66666667
    }
  },
  {
    "name": "Riley Greene",
    "line": 2.5,
    "over": {
      "american": "+115",
      "trueOdds": 2.15
    },
    "matchup": "DET Tigers @ LA Angels",
    "gameTime": "2025-05-04T20:07:00.0000000Z",
    "under": {
      "american": "-160",
      "trueOdds": 1.625
    }
  },
  {
    "name": "Freddie Freeman",
    "line": 2.5,
    "over": {
      "american": "+105",
      "trueOdds": 2.05
    },
    "matchup": "LA Dodgers @ ATL Braves",
    "gameTime": "2025-05-04T23:10:00.0000000Z",
    "under": {
      "american": "-150",
      "trueOdds": 1.66666667
    }
  },
  {
    "name": "Mookie Betts",
    "line": 2.5,
    "over": {
      "american": "+110",
      "trueOdds": 2.1
    },
    "matchup": "LA Dodgers @ ATL Braves",
    "gameTime": "2025-05-04T23:10:00.0000000Z",
    "under": {
      "american": "-155",
      "trueOdds": 1.6451613
    }
  },
  {
    "name": "Shohei Ohtani",
    "line": 2.5,
    "over": {
      "american": "+100",
      "trueOdds": 2
    },
    "matchup": "LA Dodgers @ ATL Braves",
    "gameTime": "2025-05-04T23:10:00.0000000Z",
    "under": {
      "american": "-140",
      "trueOdds": 1.71428572
    }
  }
]