[
  {
    "name": "Akira Schmid",
    "line": 20.5,
    "over": {
      "american": "-105",
      "trueOdds": 1.95238096
    },
    "matchup": "SEA Kraken @ VGK Golden Knights",
    "gameTime": "2026-02-01T03:10:00.0000000Z",
    "under": {
      "american": "-125",
      "trueOdds": 1.8
    }
  },
  {
    "name": "Karel Vejmelka",
    "line": 21.5,
    "over": {
      "american": "-125",
      "trueOdds": 1.8
    },
    "matchup": "DAL Stars @ UTA Mammoth",
    "gameTime": "2026-02-01T02:10:00.0000000Z",
    "under": {
      "american": "-105",
      "trueOdds": 1.95238096
    }
  },
  {
    "name": "Linus Ullmark",
    "line": 22.5,
    "over": {
      "american": "-110",
      "trueOdds": 1.90909091
    },
    "matchup": "NJ Devils @ OTT Senators",
    "gameTime": "2026-02-01T00:10:00.0000000Z",
    "under": {
      "american": "-120",
      "trueOdds": 1.83333334
    }
  },
  {
    "name": "Alex Lyon",
    "line": 23.5,
    "over": {
      "american": "-125",
      "trueOdds": 1.8
    },
    "matchup": "MTL Canadiens @ BUF Sabres",
    "gameTime": "2026-02-01T00:10:00.0000000Z",
    "under": {
      "american": "-105",
      "trueOdds": 1.95238096
    }
  },
  {
    "name": "Jakub Dobes",
    "line": 23.5,
    "over": {
      "american": "-105",
      "trueOdds": 1.95238096
    },
    "matchup": "MTL Canadiens @ BUF Sabres",
    "gameTime": "2026-02-01T00:10:00.0000000Z",
    "under": {
      "american": "-125",
      "trueOdds": 1.8
    }
  },
  {
    "name": "Jordan Binnington",
    "line": 23.5,
    "over": {
      "american": "-125",
      "trueOdds": 1.8
    },
    "matchup": "CBJ Blue Jackets @ STL Blues",
    "gameTime": "2026-02-01T00:10:00.0000000Z",
    "under": {
      "american": "-105",
      "trueOdds": 1.95238096
    }
  },
  {
    "name": "Jet Greaves",
    "line": 23.5,
    "over": {
      "american": "-130",
      "trueOdds": 1.76923077
    },
    "matchup": "CBJ Blue Jackets @ STL Blues",
    "gameTime": "2026-02-01T00:10:00.0000000Z",
    "under": {
      "american": "+100",
      "trueOdds": 2
    }
  },
  {
    "name": "Casey DeSmith",
    "line": 23.5,
    "over": {
      "american": "-125",
      "trueOdds": 1.8
    },
    "matchup": "DAL Stars @ UTA Mammoth",
    "gameTime": "2026-02-01T02:10:00.0000000Z",
    "under": {
      "american": "-105",
      "trueOdds": 1.95238096
    }
  },
  {
    "name": "Tristan Jarry",
    "line": 23.5,
    "over": {
      "american": "-110",
      "trueOdds": 1.90909091
    },
    "matchup": "MIN Wild @ EDM Oilers",
    "gameTime": "2026-02-01T03:10:00.0000000Z",
    "under": {
      "american": "-120",
      "trueOdds": 1.83333334
    }
  },
  {
    "name": "Ilya Sorokin",
    "line": 24.5,
    "over": {
      "american": "+100",
      "trueOdds": 2
    },
    "matchup": "NSH Predators @ NY Islanders",
    "gameTime": "2026-02-01T00:10:00.0000000Z",
    "under": {
      "american": "-130",
      "trueOdds": 1.76923077
    }
  },
  {
    "name": "Juuse Saros",
    "line": 24.5,
    "over": {
      "american": "-130",
      "trueOdds": 1.76923077
    },
    "matchup": "NSH Predators @ NY Islanders",
    "gameTime": "2026-02-01T00:10:00.0000000Z",
    "under": {
      "american": "+100",
      "trueOdds": 2
    }
  },
  {
    "name": "Jake Allen",
    "line": 24.5,
    "over": {
      "american": "-105",
      "trueOdds": 1.95238096
    },
    "matchup": "NJ Devils @ OTT Senators",
    "gameTime": "2026-02-01T00:10:00.0000000Z",
    "under": {
      "american": "-125",
      "trueOdds": 1.8
    }
  },
  {
    "name": "Jesper Wallstedt",
    "line": 26.5,
    "over": {
      "american": "-125",
      "trueOdds": 1.8
    },
    "matchup": "MIN Wild @ EDM Oilers",
    "gameTime": "2026-02-01T03:10:00.0000000Z",
    "under": {
      "american": "-105",
      "trueOdds": 1.95238096
    }
  }
]